{
    "events": [
        {
            "artistImageSrc": "https://photos.bandsintown.com/thumb/8298529.jpeg",
            "properlySizedImageURL": "https://media.bandsintown.com/110x110/8298529.webp",
            "callToActionRedirectUrl": "https://www.bandsintown.com/e/1032077050-bestial-mouths-at-scala?came_from=257&utm_medium=web&utm_source=home&utm_campaign=ticket_rsvp",
            "fallbackImageUrl": "https://assets.prod.bandsintown.com/images/homeIcon/festivalPlaceHolderImage/04.png",
            "artistName": "Bestial Mouths",
            "venueName": "Scala",
            "streamingEvent": false,
            "title": null,
            "locationText": "London, United Kingdom",
            "pinIconSrc": "https://assets.prod.bandsintown.com/images/pinIcon.svg",
            "eventUrl": "https://www.bandsintown.com/e/1032077050-bestial-mouths-at-scala?came_from=257&utm_medium=web&utm_source=home&utm_campaign=event",
            "artistUrl": "https://www.bandsintown.com/a/1024660-bestial-mouths?came_from=257&utm_medium=web&utm_source=home&utm_campaign=event",
            "watchLiveText": "Watch Live",
            "isPlus": false,
            "callToActionText": "Tickets & RSVP",
            "rsvpCount": "2",
            "rsvpCountInt": 2,
            "startsAt": "2024-10-17T19:30:00",
            "timezone": "Europe/London",
            "displayRule": "datetime",
            "locale": "en"
        },
        {
            "artistImageSrc": "https://photos.bandsintown.com/thumb/18190989.jpeg",
            "properlySizedImageURL": "https://media.bandsintown.com/110x110/18190989.webp",
            "callToActionRedirectUrl": "https://www.bandsintown.com/e/105575376-tom-vek-at-a-l-p-h-a-b-e-t?came_from=257&utm_medium=web&utm_source=home&utm_campaign=ticket_rsvp",
            "fallbackImageUrl": "https://assets.prod.bandsintown.com/images/homeIcon/festivalPlaceHolderImage/01.png",
            "artistName": "Tom Vek",
            "venueName": "A L P H A B E T",
            "streamingEvent": false,
            "title": "Tom Vek Autumn Tour",
            "locationText": "The City of Brighton and Hove, United Kingdom",
            "pinIconSrc": "https://assets.prod.bandsintown.com/images/pinIcon.svg",
            "eventUrl": "https://www.bandsintown.com/e/105575376-tom-vek-at-a-l-p-h-a-b-e-t?came_from=257&utm_medium=web&utm_source=home&utm_campaign=event",
            "artistUrl": "https://www.bandsintown.com/a/3103-tom-vek?came_from=257&utm_medium=web&utm_source=home&utm_campaign=event",
            "watchLiveText": "Watch Live",
            "isPlus": false,
            "callToActionText": "Tickets & RSVP",
            "rsvpCount": "0",
            "rsvpCountInt": 0,
            "startsAt": "2024-10-17T19:30:00",
            "timezone": "Europe/London",
            "displayRule": "datetime",
            "locale": "en"
        },
        {
            "artistImageSrc": "https://photos.bandsintown.com/thumb/13491056.jpeg",
            "properlySizedImageURL": "https://media.bandsintown.com/110x110/13491056.webp",
            "callToActionRedirectUrl": "https://www.bandsintown.com/e/1032932311-fez-at-the-old-blue-last?came_from=257&utm_medium=web&utm_source=home&utm_campaign=ticket_rsvp",
            "fallbackImageUrl": "https://assets.prod.bandsintown.com/images/homeIcon/festivalPlaceHolderImage/08.png",
            "artistName": "FEZ",
            "venueName": "The Old Blue Last",
            "streamingEvent": false,
            "title": null,
            "locationText": "Shoreditch, United Kingdom",
            "pinIconSrc": "https://assets.prod.bandsintown.com/images/pinIcon.svg",
            "eventUrl": "https://www.bandsintown.com/e/1032932311-fez-at-the-old-blue-last?came_from=257&utm_medium=web&utm_source=home&utm_campaign=event",
            "artistUrl": "https://www.bandsintown.com/a/253972-fez?came_from=257&utm_medium=web&utm_source=home&utm_campaign=event",
            "watchLiveText": "Watch Live",
            "isPlus": false,
            "callToActionText": "Tickets & RSVP",
            "rsvpCount": "0",
            "rsvpCountInt": 0,
            "startsAt": "2024-10-17T19:30:00",
            "timezone": "Europe/London",
            "displayRule": "datetime",
            "locale": "en"
        },
        {
            "artistImageSrc": "https://photos.bandsintown.com/thumb/15533244.jpeg",
            "properlySizedImageURL": "https://media.bandsintown.com/110x110/15533244.webp",
            "callToActionRedirectUrl": "https://www.bandsintown.com/e/1032688938-le-boom-at-pickle-factory?came_from=257&utm_medium=web&utm_source=home&utm_campaign=ticket_rsvp",
            "fallbackImageUrl": "https://assets.prod.bandsintown.com/images/homeIcon/festivalPlaceHolderImage/05.png",
            "artistName": "Le Boom",
            "venueName": "Pickle Factory",
            "streamingEvent": false,
            "title": null,
            "locationText": "London, United Kingdom",
            "pinIconSrc": "https://assets.prod.bandsintown.com/images/pinIcon.svg",
            "eventUrl": "https://www.bandsintown.com/e/1032688938-le-boom-at-pickle-factory?came_from=257&utm_medium=web&utm_source=home&utm_campaign=event",
            "artistUrl": "https://www.bandsintown.com/a/8152135-le-boom?came_from=257&utm_medium=web&utm_source=home&utm_campaign=event",
            "watchLiveText": "Watch Live",
            "isPlus": false,
            "callToActionText": "Tickets & RSVP",
            "rsvpCount": "0",
            "rsvpCountInt": 0,
            "startsAt": "2024-10-17T19:30:00",
            "timezone": "Europe/London",
            "displayRule": "datetime",
            "locale": "en"
        },
        {
            "artistImageSrc": "https://photos.bandsintown.com/thumb/6378796.jpeg",
            "properlySizedImageURL": "https://media.bandsintown.com/110x110/6378796.webp",
            "callToActionRedirectUrl": "https://www.bandsintown.com/e/1030957467-lebanon-hanover-at-scala?came_from=257&utm_medium=web&utm_source=home&utm_campaign=ticket_rsvp",
            "fallbackImageUrl": "https://assets.prod.bandsintown.com/images/homeIcon/festivalPlaceHolderImage/07.png",
            "artistName": "Lebanon Hanover",
            "venueName": "Scala",
            "streamingEvent": false,
            "title": null,
            "locationText": "London, United Kingdom",
            "pinIconSrc": "https://assets.prod.bandsintown.com/images/pinIcon.svg",
            "eventUrl": "https://www.bandsintown.com/e/1030957467-lebanon-hanover-at-scala?came_from=257&utm_medium=web&utm_source=home&utm_campaign=event",
            "artistUrl": "https://www.bandsintown.com/a/2131802-lebanon-hanover?came_from=257&utm_medium=web&utm_source=home&utm_campaign=event",
            "watchLiveText": "Watch Live",
            "isPlus": false,
            "callToActionText": "Tickets & RSVP",
            "rsvpCount": "83",
            "rsvpCountInt": 83,
            "startsAt": "2024-10-17T19:30:00",
            "timezone": "Europe/London",
            "displayRule": "datetime",
            "locale": "en"
        },
        {
            "artistImageSrc": "https://assets.prod.bandsintown.com/images/homeIcon/festivalPlaceHolderImage/01.png",
            "properlySizedImageURL": "https://assets.prod.bandsintown.com/images/homeIcon/festivalPlaceHolderImage/08.webp",
            "callToActionRedirectUrl": "https://www.bandsintown.com/e/1031501978-moin-at-ica?came_from=257&utm_medium=web&utm_source=home&utm_campaign=ticket_rsvp",
            "fallbackImageUrl": "https://assets.prod.bandsintown.com/images/homeIcon/festivalPlaceHolderImage/08.png",
            "artistName": "Moin",
            "venueName": "ICA",
            "streamingEvent": false,
            "title": null,
            "locationText": "London, United Kingdom",
            "pinIconSrc": "https://assets.prod.bandsintown.com/images/pinIcon.svg",
            "eventUrl": "https://www.bandsintown.com/e/1031501978-moin-at-ica?came_from=257&utm_medium=web&utm_source=home&utm_campaign=event",
            "artistUrl": "https://www.bandsintown.com/a/2980962-moin?came_from=257&utm_medium=web&utm_source=home&utm_campaign=event",
            "watchLiveText": "Watch Live",
            "isPlus": false,
            "callToActionText": "Tickets & RSVP",
            "rsvpCount": "7",
            "rsvpCountInt": 7,
            "startsAt": "2024-10-17T19:30:00",
            "timezone": "Europe/London",
            "displayRule": "datetime",
            "locale": "en"
        },
        {
            "artistImageSrc": "https://photos.bandsintown.com/thumb/7705304.jpeg",
            "properlySizedImageURL": "https://media.bandsintown.com/110x110/7705304.webp",
            "callToActionRedirectUrl": "https://www.bandsintown.com/e/1032008094-the-skints-at-bush-hall?came_from=257&utm_medium=web&utm_source=home&utm_campaign=ticket_rsvp",
            "fallbackImageUrl": "https://assets.prod.bandsintown.com/images/homeIcon/festivalPlaceHolderImage/05.png",
            "artistName": "The Skints",
            "venueName": "Bush Hall",
            "streamingEvent": false,
            "title": null,
            "locationText": "London, United Kingdom",
            "pinIconSrc": "https://assets.prod.bandsintown.com/images/pinIcon.svg",
            "eventUrl": "https://www.bandsintown.com/e/1032008094-the-skints-at-bush-hall?came_from=257&utm_medium=web&utm_source=home&utm_campaign=event",
            "artistUrl": "https://www.bandsintown.com/a/257348-the-skints?came_from=257&utm_medium=web&utm_source=home&utm_campaign=event",
            "watchLiveText": "Watch Live",
            "isPlus": false,
            "callToActionText": "Tickets & RSVP",
            "rsvpCount": "11",
            "rsvpCountInt": 11,
            "startsAt": "2024-10-17T19:30:00",
            "timezone": "Europe/London",
            "displayRule": "datetime",
            "locale": "en"
        },
        {
            "artistImageSrc": "https://photos.bandsintown.com/thumb/7742559.jpeg",
            "properlySizedImageURL": "https://media.bandsintown.com/110x110/7742559.webp",
            "callToActionRedirectUrl": "https://www.bandsintown.com/e/105189735-hungrytown-at-north-warnborough-village-hall?came_from=257&utm_medium=web&utm_source=home&utm_campaign=ticket_rsvp",
            "fallbackImageUrl": "https://assets.prod.bandsintown.com/images/homeIcon/festivalPlaceHolderImage/08.png",
            "artistName": "Hungrytown",
            "venueName": "North Warnborough Village Hall",
            "streamingEvent": false,
            "title": null,
            "locationText": "North Warnborough, United Kingdom",
            "pinIconSrc": "https://assets.prod.bandsintown.com/images/pinIcon.svg",
            "eventUrl": "https://www.bandsintown.com/e/105189735-hungrytown-at-north-warnborough-village-hall?came_from=257&utm_medium=web&utm_source=home&utm_campaign=event",
            "artistUrl": "https://www.bandsintown.com/a/322810-hungrytown?came_from=257&utm_medium=web&utm_source=home&utm_campaign=event",
            "watchLiveText": "Watch Live",
            "isPlus": false,
            "callToActionText": "Tickets & RSVP",
            "rsvpCount": "2",
            "rsvpCountInt": 2,
            "startsAt": "2024-10-17T19:30:00",
            "endsAt": "2024-10-17T21:30:00",
            "timezone": "Europe/London",
            "displayRule": "datetime",
            "locale": "en"
        },
        {
            "artistImageSrc": "https://photos.bandsintown.com/thumb/17961720.jpeg",
            "properlySizedImageURL": "https://media.bandsintown.com/110x110/17961720.webp",
            "callToActionRedirectUrl": "https://www.bandsintown.com/e/105867096-steeleye-span-at-anvil-arts?came_from=257&utm_medium=web&utm_source=home&utm_campaign=ticket_rsvp",
            "fallbackImageUrl": "https://assets.prod.bandsintown.com/images/homeIcon/festivalPlaceHolderImage/08.png",
            "artistName": "Steeleye Span",
            "venueName": "Anvil Arts",
            "streamingEvent": false,
            "title": "Steeleye Span: The 55th Anniversary Year",
            "locationText": "Basingstoke, United Kingdom",
            "pinIconSrc": "https://assets.prod.bandsintown.com/images/pinIcon.svg",
            "eventUrl": "https://www.bandsintown.com/e/105867096-steeleye-span-at-anvil-arts?came_from=257&utm_medium=web&utm_source=home&utm_campaign=event",
            "artistUrl": "https://www.bandsintown.com/a/85367-steeleye-span?came_from=257&utm_medium=web&utm_source=home&utm_campaign=event",
            "watchLiveText": "Watch Live",
            "isPlus": false,
            "callToActionText": "Tickets & RSVP",
            "rsvpCount": "3",
            "rsvpCountInt": 3,
            "startsAt": "2024-10-17T19:30:00",
            "timezone": "Europe/London",
            "displayRule": "datetime",
            "locale": "en"
        },
        {
            "artistImageSrc": "https://photos.bandsintown.com/thumb/17712698.jpeg",
            "properlySizedImageURL": "https://media.bandsintown.com/110x110/17712698.webp",
            "callToActionRedirectUrl": "https://www.bandsintown.com/e/105774892-takeaway-thieves-at-club-85?came_from=257&utm_medium=web&utm_source=home&utm_campaign=ticket_rsvp",
            "fallbackImageUrl": "https://assets.prod.bandsintown.com/images/homeIcon/festivalPlaceHolderImage/06.png",
            "artistName": "Takeaway Thieves",
            "venueName": "CLUB 85",
            "streamingEvent": false,
            "title": null,
            "locationText": "Hitchin, United Kingdom",
            "pinIconSrc": "https://assets.prod.bandsintown.com/images/pinIcon.svg",
            "eventUrl": "https://www.bandsintown.com/e/105774892-takeaway-thieves-at-club-85?came_from=257&utm_medium=web&utm_source=home&utm_campaign=event",
            "artistUrl": "https://www.bandsintown.com/a/15396956-takeaway-thieves?came_from=257&utm_medium=web&utm_source=home&utm_campaign=event",
            "watchLiveText": "Watch Live",
            "isPlus": false,
            "callToActionText": "Tickets & RSVP",
            "rsvpCount": "0",
            "rsvpCountInt": 0,
            "startsAt": "2024-10-17T19:30:00",
            "timezone": "Europe/London",
            "displayRule": "datetime",
            "locale": "en"
        },
        {
            "artistImageSrc": "https://assets.prod.bandsintown.com/images/homeIcon/festivalPlaceHolderImage/03.png",
            "properlySizedImageURL": "https://assets.prod.bandsintown.com/images/homeIcon/festivalPlaceHolderImage/05.webp",
            "callToActionRedirectUrl": "https://www.bandsintown.com/e/1033003650-queen-greatest-hits-at-the-beaverwood?came_from=257&utm_medium=web&utm_source=home&utm_campaign=ticket_rsvp",
            "fallbackImageUrl": "https://assets.prod.bandsintown.com/images/homeIcon/festivalPlaceHolderImage/01.png",
            "artistName": "QUEEN-GREATEST HITS",
            "venueName": "The Beaverwood",
            "streamingEvent": false,
            "title": null,
            "locationText": "Chislehurst, United Kingdom",
            "pinIconSrc": "https://assets.prod.bandsintown.com/images/pinIcon.svg",
            "eventUrl": "https://www.bandsintown.com/e/1033003650-queen-greatest-hits-at-the-beaverwood?came_from=257&utm_medium=web&utm_source=home&utm_campaign=event",
            "artistUrl": "https://www.bandsintown.com/a/4458720-queen-greatest-hits?came_from=257&utm_medium=web&utm_source=home&utm_campaign=event",
            "watchLiveText": "Watch Live",
            "isPlus": false,
            "callToActionText": "Tickets & RSVP",
            "rsvpCount": "0",
            "rsvpCountInt": 0,
            "startsAt": "2024-10-17T19:30:00",
            "timezone": "Europe/London",
            "displayRule": "datetime",
            "locale": "en"
        },
        {
            "artistImageSrc": "https://assets.prod.bandsintown.com/images/homeIcon/festivalPlaceHolderImage/03.png",
            "properlySizedImageURL": "https://assets.prod.bandsintown.com/images/homeIcon/festivalPlaceHolderImage/02.webp",
            "callToActionRedirectUrl": "https://www.bandsintown.com/e/1031725428-ed-gamble-at-the-anvil?came_from=257&utm_medium=web&utm_source=home&utm_campaign=ticket_rsvp",
            "fallbackImageUrl": "https://assets.prod.bandsintown.com/images/homeIcon/festivalPlaceHolderImage/01.png",
            "artistName": "Ed Gamble",
            "venueName": "The Anvil",
            "streamingEvent": false,
            "title": null,
            "locationText": "Basingstoke, United Kingdom",
            "pinIconSrc": "https://assets.prod.bandsintown.com/images/pinIcon.svg",
            "eventUrl": "https://www.bandsintown.com/e/1031725428-ed-gamble-at-the-anvil?came_from=257&utm_medium=web&utm_source=home&utm_campaign=event",
            "artistUrl": "https://www.bandsintown.com/a/979481-ed-gamble?came_from=257&utm_medium=web&utm_source=home&utm_campaign=event",
            "watchLiveText": "Watch Live",
            "isPlus": false,
            "callToActionText": "Tickets & RSVP",
            "rsvpCount": "0",
            "rsvpCountInt": 0,
            "startsAt": "2024-10-17T19:30:00",
            "timezone": "Europe/London",
            "displayRule": "datetime",
            "locale": "en"
        },
        {
            "artistImageSrc": "https://photos.bandsintown.com/thumb/17283042.jpeg",
            "properlySizedImageURL": "https://media.bandsintown.com/110x110/17283042.webp",
            "callToActionRedirectUrl": "https://www.bandsintown.com/e/1032092542-maisie-adam-at-the-clapham-grand?came_from=257&utm_medium=web&utm_source=home&utm_campaign=ticket_rsvp",
            "fallbackImageUrl": "https://assets.prod.bandsintown.com/images/homeIcon/festivalPlaceHolderImage/06.png",
            "artistName": "Maisie Adam",
            "venueName": "The Clapham Grand",
            "streamingEvent": false,
            "title": null,
            "locationText": "London, United Kingdom",
            "pinIconSrc": "https://assets.prod.bandsintown.com/images/pinIcon.svg",
            "eventUrl": "https://www.bandsintown.com/e/1032092542-maisie-adam-at-the-clapham-grand?came_from=257&utm_medium=web&utm_source=home&utm_campaign=event",
            "artistUrl": "https://www.bandsintown.com/a/15548300-maisie-adam?came_from=257&utm_medium=web&utm_source=home&utm_campaign=event",
            "watchLiveText": "Watch Live",
            "isPlus": false,
            "callToActionText": "Tickets & RSVP",
            "rsvpCount": "0",
            "rsvpCountInt": 0,
            "startsAt": "2024-10-17T19:30:00",
            "timezone": "Europe/London",
            "displayRule": "datetime",
            "locale": "en"
        },
        {
            "artistImageSrc": "https://photos.bandsintown.com/thumb/17619397.jpeg",
            "properlySizedImageURL": "https://media.bandsintown.com/110x110/17619397.webp",
            "callToActionRedirectUrl": "https://www.bandsintown.com/e/105744068-ebony-buckle-at-the-camden-club?came_from=257&utm_medium=web&utm_source=home&utm_campaign=ticket_rsvp",
            "fallbackImageUrl": "https://assets.prod.bandsintown.com/images/homeIcon/festivalPlaceHolderImage/04.png",
            "artistName": "Ebony Buckle",
            "venueName": "The Camden Club",
            "streamingEvent": false,
            "title": "Ebony Buckle - Album Launch Party",
            "locationText": "London, United Kingdom",
            "pinIconSrc": "https://assets.prod.bandsintown.com/images/pinIcon.svg",
            "eventUrl": "https://www.bandsintown.com/e/105744068-ebony-buckle-at-the-camden-club?came_from=257&utm_medium=web&utm_source=home&utm_campaign=event",
            "artistUrl": "https://www.bandsintown.com/a/13265664-ebony-buckle?came_from=257&utm_medium=web&utm_source=home&utm_campaign=event",
            "watchLiveText": "Watch Live",
            "isPlus": false,
            "callToActionText": "Tickets & RSVP",
            "rsvpCount": "2",
            "rsvpCountInt": 2,
            "startsAt": "2024-10-17T19:30:00",
            "endsAt": "2024-10-17T23:00:00",
            "timezone": "Europe/London",
            "displayRule": "datetime",
            "locale": "en"
        },
        {
            "artistImageSrc": "https://photos.bandsintown.com/thumb/8379095.jpeg",
            "properlySizedImageURL": "https://media.bandsintown.com/110x110/8379095.webp",
            "callToActionRedirectUrl": "https://www.bandsintown.com/e/1033060378-mar-at-the-four-thieves?came_from=257&utm_medium=web&utm_source=home&utm_campaign=ticket_rsvp",
            "fallbackImageUrl": "https://assets.prod.bandsintown.com/images/homeIcon/festivalPlaceHolderImage/04.png",
            "artistName": "Mar",
            "venueName": "The Four Thieves",
            "streamingEvent": false,
            "title": null,
            "locationText": "London, United Kingdom",
            "pinIconSrc": "https://assets.prod.bandsintown.com/images/pinIcon.svg",
            "eventUrl": "https://www.bandsintown.com/e/1033060378-mar-at-the-four-thieves?came_from=257&utm_medium=web&utm_source=home&utm_campaign=event",
            "artistUrl": "https://www.bandsintown.com/a/32960-mar?came_from=257&utm_medium=web&utm_source=home&utm_campaign=event",
            "watchLiveText": "Watch Live",
            "isPlus": false,
            "callToActionText": "Tickets & RSVP",
            "rsvpCount": "0",
            "rsvpCountInt": 0,
            "startsAt": "2024-10-17T19:30:00",
            "timezone": "Europe/London",
            "displayRule": "datetime",
            "locale": "en"
        },
        {
            "artistImageSrc": "https://photos.bandsintown.com/thumb/18115705.jpeg",
            "properlySizedImageURL": "https://media.bandsintown.com/110x110/18115705.webp",
            "callToActionRedirectUrl": "https://www.bandsintown.com/e/1033060607-the-xaviers-at-the-four-thieves?came_from=257&utm_medium=web&utm_source=home&utm_campaign=ticket_rsvp",
            "fallbackImageUrl": "https://assets.prod.bandsintown.com/images/homeIcon/festivalPlaceHolderImage/08.png",
            "artistName": "The Xaviers",
            "venueName": "The Four Thieves",
            "streamingEvent": false,
            "title": null,
            "locationText": "London, United Kingdom",
            "pinIconSrc": "https://assets.prod.bandsintown.com/images/pinIcon.svg",
            "eventUrl": "https://www.bandsintown.com/e/1033060607-the-xaviers-at-the-four-thieves?came_from=257&utm_medium=web&utm_source=home&utm_campaign=event",
            "artistUrl": "https://www.bandsintown.com/a/15557652-the-xaviers?came_from=257&utm_medium=web&utm_source=home&utm_campaign=event",
            "watchLiveText": "Watch Live",
            "isPlus": false,
            "callToActionText": "Tickets & RSVP",
            "rsvpCount": "0",
            "rsvpCountInt": 0,
            "startsAt": "2024-10-17T19:30:00",
            "timezone": "Europe/London",
            "displayRule": "datetime",
            "locale": "en"
        },
        {
            "artistImageSrc": "https://photos.bandsintown.com/thumb/17896844.jpeg",
            "properlySizedImageURL": "https://media.bandsintown.com/110x110/17896844.webp",
            "callToActionRedirectUrl": "https://www.bandsintown.com/e/105314121-john-grant-at-hackney-church?came_from=257&utm_medium=web&utm_source=home&utm_campaign=ticket_rsvp",
            "fallbackImageUrl": "https://assets.prod.bandsintown.com/images/homeIcon/festivalPlaceHolderImage/03.png",
            "artistName": "John Grant",
            "venueName": "Hackney Church",
            "streamingEvent": false,
            "title": null,
            "locationText": "London, United Kingdom",
            "pinIconSrc": "https://assets.prod.bandsintown.com/images/pinIcon.svg",
            "eventUrl": "https://www.bandsintown.com/e/105314121-john-grant-at-hackney-church?came_from=257&utm_medium=web&utm_source=home&utm_campaign=event",
            "artistUrl": "https://www.bandsintown.com/a/947474-john-grant?came_from=257&utm_medium=web&utm_source=home&utm_campaign=event",
            "watchLiveText": "Watch Live",
            "isPlus": false,
            "callToActionText": "Tickets & RSVP",
            "rsvpCount": "181",
            "rsvpCountInt": 181,
            "startsAt": "2024-10-17T19:30:00",
            "endsAt": "2024-10-17T23:00:00",
            "timezone": "Europe/London",
            "displayRule": "datetime",
            "locale": "en"
        },
        {
            "artistImageSrc": "https://photos.bandsintown.com/thumb/15637406.jpeg",
            "properlySizedImageURL": "https://media.bandsintown.com/110x110/15637406.webp",
            "callToActionRedirectUrl": "https://www.bandsintown.com/e/1032972059-chloe-foy-at-paper-dress-vintage?came_from=257&utm_medium=web&utm_source=home&utm_campaign=ticket_rsvp",
            "fallbackImageUrl": "https://assets.prod.bandsintown.com/images/homeIcon/festivalPlaceHolderImage/06.png",
            "artistName": "Chloe Foy",
            "venueName": "Paper Dress Vintage",
            "streamingEvent": false,
            "title": null,
            "locationText": "London, United Kingdom",
            "pinIconSrc": "https://assets.prod.bandsintown.com/images/pinIcon.svg",
            "eventUrl": "https://www.bandsintown.com/e/1032972059-chloe-foy-at-paper-dress-vintage?came_from=257&utm_medium=web&utm_source=home&utm_campaign=event",
            "artistUrl": "https://www.bandsintown.com/a/2687577-chloe-foy?came_from=257&utm_medium=web&utm_source=home&utm_campaign=event",
            "watchLiveText": "Watch Live",
            "isPlus": false,
            "callToActionText": "Tickets & RSVP",
            "rsvpCount": "3",
            "rsvpCountInt": 3,
            "startsAt": "2024-10-17T19:30:00",
            "timezone": "Europe/London",
            "displayRule": "datetime",
            "locale": "en"
        },
        {
            "artistImageSrc": "https://photos.bandsintown.com/thumb/17353121.jpeg",
            "properlySizedImageURL": "https://media.bandsintown.com/110x110/17353121.webp",
            "callToActionRedirectUrl": "https://www.bandsintown.com/e/105636678-the-sound-of-springsteen-at-churchill-theatre?came_from=257&utm_medium=web&utm_source=home&utm_campaign=ticket_rsvp",
            "fallbackImageUrl": "https://assets.prod.bandsintown.com/images/homeIcon/festivalPlaceHolderImage/03.png",
            "artistName": "The Sound Of Springsteen",
            "venueName": "Churchill Theatre",
            "streamingEvent": false,
            "title": null,
            "locationText": "Bromley, United Kingdom",
            "pinIconSrc": "https://assets.prod.bandsintown.com/images/pinIcon.svg",
            "eventUrl": "https://www.bandsintown.com/e/105636678-the-sound-of-springsteen-at-churchill-theatre?came_from=257&utm_medium=web&utm_source=home&utm_campaign=event",
            "artistUrl": "https://www.bandsintown.com/a/15374075-the-sound-of-springsteen?came_from=257&utm_medium=web&utm_source=home&utm_campaign=event",
            "watchLiveText": "Watch Live",
            "isPlus": false,
            "callToActionText": "Tickets & RSVP",
            "rsvpCount": "5",
            "rsvpCountInt": 5,
            "startsAt": "2024-10-17T19:30:00",
            "timezone": "Europe/London",
            "displayRule": "datetime",
            "locale": "en"
        },
        {
            "artistImageSrc": "https://photos.bandsintown.com/thumb/8500124.jpeg",
            "properlySizedImageURL": "https://media.bandsintown.com/110x110/8500124.webp",
            "callToActionRedirectUrl": "https://www.bandsintown.com/e/1033179541-azekel-at-ladbroke-hall?came_from=257&utm_medium=web&utm_source=home&utm_campaign=ticket_rsvp",
            "fallbackImageUrl": "https://assets.prod.bandsintown.com/images/homeIcon/festivalPlaceHolderImage/01.png",
            "artistName": "Azekel",
            "venueName": "Ladbroke Hall",
            "streamingEvent": false,
            "title": null,
            "locationText": "London, United Kingdom",
            "pinIconSrc": "https://assets.prod.bandsintown.com/images/pinIcon.svg",
            "eventUrl": "https://www.bandsintown.com/e/1033179541-azekel-at-ladbroke-hall?came_from=257&utm_medium=web&utm_source=home&utm_campaign=event",
            "artistUrl": "https://www.bandsintown.com/a/2138619-azekel?came_from=257&utm_medium=web&utm_source=home&utm_campaign=event",
            "watchLiveText": "Watch Live",
            "isPlus": false,
            "callToActionText": "Tickets & RSVP",
            "rsvpCount": "1",
            "rsvpCountInt": 1,
            "startsAt": "2024-10-17T19:30:00",
            "timezone": "Europe/London",
            "displayRule": "datetime",
            "locale": "en"
        },
        {
            "artistImageSrc": "https://photos.bandsintown.com/thumb/18167481.jpeg",
            "properlySizedImageURL": "https://media.bandsintown.com/110x110/18167481.webp",
            "callToActionRedirectUrl": "https://www.bandsintown.com/e/105938406-later-youth-at-paper-dress-vintage?came_from=257&utm_medium=web&utm_source=home&utm_campaign=ticket_rsvp",
            "fallbackImageUrl": "https://assets.prod.bandsintown.com/images/homeIcon/festivalPlaceHolderImage/01.png",
            "artistName": "LATER YOUTH",
            "venueName": "Paper Dress Vintage",
            "streamingEvent": false,
            "title": "Later Youth + Chloe Foy @ Paper Dress Vintage",
            "locationText": "London, United Kingdom",
            "pinIconSrc": "https://assets.prod.bandsintown.com/images/pinIcon.svg",
            "eventUrl": "https://www.bandsintown.com/e/105938406-later-youth-at-paper-dress-vintage?came_from=257&utm_medium=web&utm_source=home&utm_campaign=event",
            "artistUrl": "https://www.bandsintown.com/a/15395070-later-youth?came_from=257&utm_medium=web&utm_source=home&utm_campaign=event",
            "watchLiveText": "Watch Live",
            "isPlus": false,
            "callToActionText": "Tickets & RSVP",
            "rsvpCount": "1",
            "rsvpCountInt": 1,
            "startsAt": "2024-10-17T19:30:00",
            "endsAt": "2024-10-17T23:59:00",
            "timezone": "Europe/London",
            "displayRule": "datetime",
            "locale": "en"
        },
        {
            "artistImageSrc": "https://assets.prod.bandsintown.com/images/homeIcon/festivalPlaceHolderImage/06.png",
            "properlySizedImageURL": "https://assets.prod.bandsintown.com/images/homeIcon/festivalPlaceHolderImage/06.webp",
            "callToActionRedirectUrl": "https://www.bandsintown.com/e/1032892452-olan-monk-at-ica-(institute-of-contemporary-arts)?came_from=257&utm_medium=web&utm_source=home&utm_campaign=ticket_rsvp",
            "fallbackImageUrl": "https://assets.prod.bandsintown.com/images/homeIcon/festivalPlaceHolderImage/06.png",
            "artistName": "OLAN MONK",
            "venueName": "ICA (Institute of Contemporary Arts)",
            "streamingEvent": false,
            "title": null,
            "locationText": "London, United Kingdom",
            "pinIconSrc": "https://assets.prod.bandsintown.com/images/pinIcon.svg",
            "eventUrl": "https://www.bandsintown.com/e/1032892452-olan-monk-at-ica-(institute-of-contemporary-arts)?came_from=257&utm_medium=web&utm_source=home&utm_campaign=event",
            "artistUrl": "https://www.bandsintown.com/a/13521027-olan-monk?came_from=257&utm_medium=web&utm_source=home&utm_campaign=event",
            "watchLiveText": "Watch Live",
            "isPlus": false,
            "callToActionText": "Tickets & RSVP",
            "rsvpCount": "0",
            "rsvpCountInt": 0,
            "startsAt": "2024-10-17T19:30:00",
            "timezone": "Europe/London",
            "displayRule": "datetime",
            "locale": "en"
        },
        {
            "artistImageSrc": "https://photos.bandsintown.com/thumb/16366495.jpeg",
            "properlySizedImageURL": "https://media.bandsintown.com/110x110/16366495.webp",
            "callToActionRedirectUrl": "https://www.bandsintown.com/e/1033204280-the-kobras-at-the-old-blue-last?came_from=257&utm_medium=web&utm_source=home&utm_campaign=ticket_rsvp",
            "fallbackImageUrl": "https://assets.prod.bandsintown.com/images/homeIcon/festivalPlaceHolderImage/01.png",
            "artistName": "The Kobras",
            "venueName": "The Old Blue Last",
            "streamingEvent": false,
            "title": null,
            "locationText": "Shoreditch, United Kingdom",
            "pinIconSrc": "https://assets.prod.bandsintown.com/images/pinIcon.svg",
            "eventUrl": "https://www.bandsintown.com/e/1033204280-the-kobras-at-the-old-blue-last?came_from=257&utm_medium=web&utm_source=home&utm_campaign=event",
            "artistUrl": "https://www.bandsintown.com/a/15535268-the-kobras?came_from=257&utm_medium=web&utm_source=home&utm_campaign=event",
            "watchLiveText": "Watch Live",
            "isPlus": false,
            "callToActionText": "Tickets & RSVP",
            "rsvpCount": "0",
            "rsvpCountInt": 0,
            "startsAt": "2024-10-17T19:30:00",
            "timezone": "Europe/London",
            "displayRule": "datetime",
            "locale": "en"
        },
        {
            "artistImageSrc": "https://assets.prod.bandsintown.com/images/homeIcon/festivalPlaceHolderImage/04.png",
            "properlySizedImageURL": "https://assets.prod.bandsintown.com/images/homeIcon/festivalPlaceHolderImage/04.webp",
            "callToActionRedirectUrl": "https://www.bandsintown.com/e/1032932127-dreamwave-at-the-old-blue-last?came_from=257&utm_medium=web&utm_source=home&utm_campaign=ticket_rsvp",
            "fallbackImageUrl": "https://assets.prod.bandsintown.com/images/homeIcon/festivalPlaceHolderImage/01.png",
            "artistName": "Dreamwave",
            "venueName": "The Old Blue Last",
            "streamingEvent": false,
            "title": null,
            "locationText": "Shoreditch, United Kingdom",
            "pinIconSrc": "https://assets.prod.bandsintown.com/images/pinIcon.svg",
            "eventUrl": "https://www.bandsintown.com/e/1032932127-dreamwave-at-the-old-blue-last?came_from=257&utm_medium=web&utm_source=home&utm_campaign=event",
            "artistUrl": "https://www.bandsintown.com/a/1874297-dreamwave?came_from=257&utm_medium=web&utm_source=home&utm_campaign=event",
            "watchLiveText": "Watch Live",
            "isPlus": false,
            "callToActionText": "Tickets & RSVP",
            "rsvpCount": "0",
            "rsvpCountInt": 0,
            "startsAt": "2024-10-17T19:30:00",
            "timezone": "Europe/London",
            "displayRule": "datetime",
            "locale": "en"
        },
        {
            "artistImageSrc": "https://assets.prod.bandsintown.com/images/homeIcon/festivalPlaceHolderImage/01.png",
            "properlySizedImageURL": "https://assets.prod.bandsintown.com/images/homeIcon/festivalPlaceHolderImage/06.webp",
            "callToActionRedirectUrl": "https://www.bandsintown.com/e/1032445741-luiz-bruno-at-two-palms?came_from=257&utm_medium=web&utm_source=home&utm_campaign=ticket_rsvp",
            "fallbackImageUrl": "https://assets.prod.bandsintown.com/images/homeIcon/festivalPlaceHolderImage/07.png",
            "artistName": "Luiz Bruno",
            "venueName": "TWO PALMS",
            "streamingEvent": false,
            "title": null,
            "locationText": "London, United Kingdom",
            "pinIconSrc": "https://assets.prod.bandsintown.com/images/pinIcon.svg",
            "eventUrl": "https://www.bandsintown.com/e/1032445741-luiz-bruno-at-two-palms?came_from=257&utm_medium=web&utm_source=home&utm_campaign=event",
            "artistUrl": "https://www.bandsintown.com/a/14661016-luiz-bruno?came_from=257&utm_medium=web&utm_source=home&utm_campaign=event",
            "watchLiveText": "Watch Live",
            "isPlus": false,
            "callToActionText": "Tickets & RSVP",
            "rsvpCount": "0",
            "rsvpCountInt": 0,
            "startsAt": "2024-10-17T19:30:00",
            "timezone": "Europe/London",
            "displayRule": "datetime",
            "locale": "en"
        },
        {
            "artistImageSrc": "https://photos.bandsintown.com/thumb/14149473.jpeg",
            "properlySizedImageURL": "https://media.bandsintown.com/110x110/14149473.webp",
            "callToActionRedirectUrl": "https://www.bandsintown.com/e/1032119161-sivu-at-st-pancras-old-church?came_from=257&utm_medium=web&utm_source=home&utm_campaign=ticket_rsvp",
            "fallbackImageUrl": "https://assets.prod.bandsintown.com/images/homeIcon/festivalPlaceHolderImage/08.png",
            "artistName": "Sivu",
            "venueName": "St Pancras Old Church",
            "streamingEvent": false,
            "title": null,
            "locationText": "North London, United Kingdom",
            "pinIconSrc": "https://assets.prod.bandsintown.com/images/pinIcon.svg",
            "eventUrl": "https://www.bandsintown.com/e/1032119161-sivu-at-st-pancras-old-church?came_from=257&utm_medium=web&utm_source=home&utm_campaign=event",
            "artistUrl": "https://www.bandsintown.com/a/4706282-sivu?came_from=257&utm_medium=web&utm_source=home&utm_campaign=event",
            "watchLiveText": "Watch Live",
            "isPlus": false,
            "callToActionText": "Tickets & RSVP",
            "rsvpCount": "0",
            "rsvpCountInt": 0,
            "startsAt": "2024-10-17T19:30:00",
            "timezone": "Europe/London",
            "displayRule": "datetime",
            "locale": "en"
        },
        {
            "artistImageSrc": "https://photos.bandsintown.com/thumb/16658655.jpeg",
            "properlySizedImageURL": "https://media.bandsintown.com/110x110/16658655.webp",
            "callToActionRedirectUrl": "https://www.bandsintown.com/e/1032922137-cristina-hart-at-the-garage?came_from=257&utm_medium=web&utm_source=home&utm_campaign=ticket_rsvp",
            "fallbackImageUrl": "https://assets.prod.bandsintown.com/images/homeIcon/festivalPlaceHolderImage/07.png",
            "artistName": "Cristina Hart",
            "venueName": "The Garage",
            "streamingEvent": false,
            "title": null,
            "locationText": "London, United Kingdom",
            "pinIconSrc": "https://assets.prod.bandsintown.com/images/pinIcon.svg",
            "eventUrl": "https://www.bandsintown.com/e/1032922137-cristina-hart-at-the-garage?came_from=257&utm_medium=web&utm_source=home&utm_campaign=event",
            "artistUrl": "https://www.bandsintown.com/a/15017511-cristina-hart?came_from=257&utm_medium=web&utm_source=home&utm_campaign=event",
            "watchLiveText": "Watch Live",
            "isPlus": false,
            "callToActionText": "Tickets & RSVP",
            "rsvpCount": "0",
            "rsvpCountInt": 0,
            "startsAt": "2024-10-17T19:30:00",
            "timezone": "Europe/London",
            "displayRule": "datetime",
            "locale": "en"
        },
        {
            "artistImageSrc": "https://photos.bandsintown.com/thumb/18233061.jpeg",
            "properlySizedImageURL": "https://media.bandsintown.com/110x110/18233061.webp",
            "callToActionRedirectUrl": "https://www.bandsintown.com/e/105956843-slate-at-100-club?came_from=257&utm_medium=web&utm_source=home&utm_campaign=ticket_rsvp",
            "fallbackImageUrl": "https://assets.prod.bandsintown.com/images/homeIcon/festivalPlaceHolderImage/02.png",
            "artistName": "slate",
            "venueName": "100 Club",
            "streamingEvent": false,
            "title": "100 Club ",
            "locationText": "London, United Kingdom",
            "pinIconSrc": "https://assets.prod.bandsintown.com/images/pinIcon.svg",
            "eventUrl": "https://www.bandsintown.com/e/105956843-slate-at-100-club?came_from=257&utm_medium=web&utm_source=home&utm_campaign=event",
            "artistUrl": "https://www.bandsintown.com/a/15541412-slate?came_from=257&utm_medium=web&utm_source=home&utm_campaign=event",
            "watchLiveText": "Watch Live",
            "isPlus": false,
            "callToActionText": "Tickets & RSVP",
            "rsvpCount": "1",
            "rsvpCountInt": 1,
            "startsAt": "2024-10-17T19:30:00",
            "endsAt": "2024-10-17T23:00:00",
            "timezone": "Europe/London",
            "displayRule": "datetime",
            "locale": "en"
        },
        {
            "artistImageSrc": "https://photos.bandsintown.com/thumb/6335136.jpeg",
            "properlySizedImageURL": "https://media.bandsintown.com/110x110/6335136.webp",
            "callToActionRedirectUrl": "https://www.bandsintown.com/e/1031759367-no-cars-at-two-palms?came_from=257&utm_medium=web&utm_source=home&utm_campaign=ticket_rsvp",
            "fallbackImageUrl": "https://assets.prod.bandsintown.com/images/homeIcon/festivalPlaceHolderImage/01.png",
            "artistName": "No Cars",
            "venueName": "TWO PALMS",
            "streamingEvent": false,
            "title": null,
            "locationText": "London, United Kingdom",
            "pinIconSrc": "https://assets.prod.bandsintown.com/images/pinIcon.svg",
            "eventUrl": "https://www.bandsintown.com/e/1031759367-no-cars-at-two-palms?came_from=257&utm_medium=web&utm_source=home&utm_campaign=event",
            "artistUrl": "https://www.bandsintown.com/a/224800-no-cars?came_from=257&utm_medium=web&utm_source=home&utm_campaign=event",
            "watchLiveText": "Watch Live",
            "isPlus": false,
            "callToActionText": "Tickets & RSVP",
            "rsvpCount": "1",
            "rsvpCountInt": 1,
            "startsAt": "2024-10-17T19:30:00",
            "timezone": "Europe/London",
            "displayRule": "datetime",
            "locale": "en"
        },
        {
            "artistImageSrc": "https://photos.bandsintown.com/thumb/17022753.jpeg",
            "properlySizedImageURL": "https://media.bandsintown.com/110x110/17022753.webp",
            "callToActionRedirectUrl": "https://www.bandsintown.com/e/1031759224-lovell-at-two-palms?came_from=257&utm_medium=web&utm_source=home&utm_campaign=ticket_rsvp",
            "fallbackImageUrl": "https://assets.prod.bandsintown.com/images/homeIcon/festivalPlaceHolderImage/05.png",
            "artistName": "LOVELL",
            "venueName": "TWO PALMS",
            "streamingEvent": false,
            "title": null,
            "locationText": "London, United Kingdom",
            "pinIconSrc": "https://assets.prod.bandsintown.com/images/pinIcon.svg",
            "eventUrl": "https://www.bandsintown.com/e/1031759224-lovell-at-two-palms?came_from=257&utm_medium=web&utm_source=home&utm_campaign=event",
            "artistUrl": "https://www.bandsintown.com/a/14040182-lovell?came_from=257&utm_medium=web&utm_source=home&utm_campaign=event",
            "watchLiveText": "Watch Live",
            "isPlus": false,
            "callToActionText": "Tickets & RSVP",
            "rsvpCount": "1",
            "rsvpCountInt": 1,
            "startsAt": "2024-10-17T19:30:00",
            "timezone": "Europe/London",
            "displayRule": "datetime",
            "locale": "en"
        },
        {
            "artistImageSrc": "https://photos.bandsintown.com/thumb/18349996.jpeg",
            "properlySizedImageURL": "https://media.bandsintown.com/110x110/18349996.webp",
            "callToActionRedirectUrl": "https://www.bandsintown.com/e/1033007087-tell-a-vision-at-new-river-studios?came_from=257&utm_medium=web&utm_source=home&utm_campaign=ticket_rsvp",
            "fallbackImageUrl": "https://assets.prod.bandsintown.com/images/homeIcon/festivalPlaceHolderImage/04.png",
            "artistName": "TEll A ViSiON",
            "venueName": "New River Studios",
            "streamingEvent": false,
            "title": null,
            "locationText": "London, United Kingdom",
            "pinIconSrc": "https://assets.prod.bandsintown.com/images/pinIcon.svg",
            "eventUrl": "https://www.bandsintown.com/e/1033007087-tell-a-vision-at-new-river-studios?came_from=257&utm_medium=web&utm_source=home&utm_campaign=event",
            "artistUrl": "https://www.bandsintown.com/a/1739748-tell-a-vision?came_from=257&utm_medium=web&utm_source=home&utm_campaign=event",
            "watchLiveText": "Watch Live",
            "isPlus": false,
            "callToActionText": "Tickets & RSVP",
            "rsvpCount": "1",
            "rsvpCountInt": 1,
            "startsAt": "2024-10-17T19:30:00",
            "timezone": "Europe/London",
            "displayRule": "datetime",
            "locale": "en"
        },
        {
            "artistImageSrc": "https://assets.prod.bandsintown.com/images/homeIcon/festivalPlaceHolderImage/04.png",
            "properlySizedImageURL": "https://assets.prod.bandsintown.com/images/homeIcon/festivalPlaceHolderImage/02.webp",
            "callToActionRedirectUrl": "https://www.bandsintown.com/e/1033004138-music-:)-at-indian-essence-restaurant?came_from=257&utm_medium=web&utm_source=home&utm_campaign=ticket_rsvp",
            "fallbackImageUrl": "https://assets.prod.bandsintown.com/images/homeIcon/festivalPlaceHolderImage/07.png",
            "artistName": "music :)",
            "venueName": "Indian Essence Restaurant",
            "streamingEvent": false,
            "title": null,
            "locationText": "Bromley, United Kingdom",
            "pinIconSrc": "https://assets.prod.bandsintown.com/images/pinIcon.svg",
            "eventUrl": "https://www.bandsintown.com/e/1033004138-music-:)-at-indian-essence-restaurant?came_from=257&utm_medium=web&utm_source=home&utm_campaign=event",
            "artistUrl": "https://www.bandsintown.com/a/1159079-music-:)?came_from=257&utm_medium=web&utm_source=home&utm_campaign=event",
            "watchLiveText": "Watch Live",
            "isPlus": false,
            "callToActionText": "Tickets & RSVP",
            "rsvpCount": "0",
            "rsvpCountInt": 0,
            "startsAt": "2024-10-17T19:30:00",
            "timezone": "Europe/London",
            "displayRule": "datetime",
            "locale": "en"
        },
        {
            "artistImageSrc": "https://photos.bandsintown.com/thumb/16698776.jpeg",
            "properlySizedImageURL": "https://media.bandsintown.com/110x110/16698776.webp",
            "callToActionRedirectUrl": "https://www.bandsintown.com/e/1031445590-dave-stapleton-at-world-heart-beat-embassy-gardens?came_from=257&utm_medium=web&utm_source=home&utm_campaign=ticket_rsvp",
            "fallbackImageUrl": "https://assets.prod.bandsintown.com/images/homeIcon/festivalPlaceHolderImage/08.png",
            "artistName": "Dave Stapleton",
            "venueName": "World Heart Beat Embassy Gardens",
            "streamingEvent": false,
            "title": null,
            "locationText": "London, United Kingdom",
            "pinIconSrc": "https://assets.prod.bandsintown.com/images/pinIcon.svg",
            "eventUrl": "https://www.bandsintown.com/e/1031445590-dave-stapleton-at-world-heart-beat-embassy-gardens?came_from=257&utm_medium=web&utm_source=home&utm_campaign=event",
            "artistUrl": "https://www.bandsintown.com/a/739405-dave-stapleton?came_from=257&utm_medium=web&utm_source=home&utm_campaign=event",
            "watchLiveText": "Watch Live",
            "isPlus": false,
            "callToActionText": "Tickets & RSVP",
            "rsvpCount": "10",
            "rsvpCountInt": 10,
            "startsAt": "2024-10-17T19:30:00",
            "endsAt": "2024-10-17T22:30:00",
            "timezone": "Europe/London",
            "displayRule": "datetime",
            "locale": "en"
        },
        {
            "artistImageSrc": "https://photos.bandsintown.com/thumb/16710929.jpeg",
            "properlySizedImageURL": "https://media.bandsintown.com/110x110/16710929.webp",
            "callToActionRedirectUrl": "https://www.bandsintown.com/e/1031500370-garrison-keillor-at-cadogan-hall?came_from=257&utm_medium=web&utm_source=home&utm_campaign=ticket_rsvp",
            "fallbackImageUrl": "https://assets.prod.bandsintown.com/images/homeIcon/festivalPlaceHolderImage/02.png",
            "artistName": "Garrison Keillor",
            "venueName": "Cadogan Hall",
            "streamingEvent": false,
            "title": null,
            "locationText": "London, United Kingdom",
            "pinIconSrc": "https://assets.prod.bandsintown.com/images/pinIcon.svg",
            "eventUrl": "https://www.bandsintown.com/e/1031500370-garrison-keillor-at-cadogan-hall?came_from=257&utm_medium=web&utm_source=home&utm_campaign=event",
            "artistUrl": "https://www.bandsintown.com/a/46464-garrison-keillor?came_from=257&utm_medium=web&utm_source=home&utm_campaign=event",
            "watchLiveText": "Watch Live",
            "isPlus": false,
            "callToActionText": "Tickets & RSVP",
            "rsvpCount": "2",
            "rsvpCountInt": 2,
            "startsAt": "2024-10-17T19:30:00",
            "timezone": "Europe/London",
            "displayRule": "datetime",
            "locale": "en"
        },
        {
            "artistImageSrc": "https://photos.bandsintown.com/thumb/17505432.jpeg",
            "properlySizedImageURL": "https://media.bandsintown.com/110x110/17505432.webp",
            "callToActionRedirectUrl": "https://www.bandsintown.com/e/105700181-music-by-march-at-servant-jazz-quarters?came_from=257&utm_medium=web&utm_source=home&utm_campaign=ticket_rsvp",
            "fallbackImageUrl": "https://assets.prod.bandsintown.com/images/homeIcon/festivalPlaceHolderImage/05.png",
            "artistName": "music by march",
            "venueName": "Servant Jazz Quarters",
            "streamingEvent": false,
            "title": "march: Cross St Demos EP pre-release @ SJQ",
            "locationText": "London, United Kingdom",
            "pinIconSrc": "https://assets.prod.bandsintown.com/images/pinIcon.svg",
            "eventUrl": "https://www.bandsintown.com/e/105700181-music-by-march-at-servant-jazz-quarters?came_from=257&utm_medium=web&utm_source=home&utm_campaign=event",
            "artistUrl": "https://www.bandsintown.com/a/6020986-music-by-march?came_from=257&utm_medium=web&utm_source=home&utm_campaign=event",
            "watchLiveText": "Watch Live",
            "isPlus": false,
            "callToActionText": "Tickets & RSVP",
            "rsvpCount": "6",
            "rsvpCountInt": 6,
            "startsAt": "2024-10-17T19:30:00",
            "timezone": "Europe/London",
            "displayRule": "datetime",
            "locale": "en"
        },
        {
            "artistImageSrc": "https://assets.prod.bandsintown.com/images/homeIcon/festivalPlaceHolderImage/01.png",
            "properlySizedImageURL": "https://assets.prod.bandsintown.com/images/homeIcon/festivalPlaceHolderImage/07.webp",
            "callToActionRedirectUrl": "https://www.bandsintown.com/e/1032765719-nightbus-at-100-club?came_from=257&utm_medium=web&utm_source=home&utm_campaign=ticket_rsvp",
            "fallbackImageUrl": "https://assets.prod.bandsintown.com/images/homeIcon/festivalPlaceHolderImage/05.png",
            "artistName": "Nightbus",
            "venueName": "100 Club",
            "streamingEvent": false,
            "title": null,
            "locationText": "London, United Kingdom",
            "pinIconSrc": "https://assets.prod.bandsintown.com/images/pinIcon.svg",
            "eventUrl": "https://www.bandsintown.com/e/1032765719-nightbus-at-100-club?came_from=257&utm_medium=web&utm_source=home&utm_campaign=event",
            "artistUrl": "https://www.bandsintown.com/a/965172-nightbus?came_from=257&utm_medium=web&utm_source=home&utm_campaign=event",
            "watchLiveText": "Watch Live",
            "isPlus": false,
            "callToActionText": "Tickets & RSVP",
            "rsvpCount": "0",
            "rsvpCountInt": 0,
            "startsAt": "2024-10-17T19:30:00",
            "timezone": "Europe/London",
            "displayRule": "datetime",
            "locale": "en"
        }
    ],
    "urlForNextPageOfEvents": "https://www.bandsintown.com/choose-dates/fetch-next/upcomingEvents?city_id=2643743&date=2024-10-17T00%3A00%3A00%2C2024-10-17T23%3A59%3A59&page=5&longitude=-0.12574&latitude=51.50853&genre_query=all-genres",
    "userLocation": null
}