{
    "events": [
        {
            "artistImageSrc": "https://photos.bandsintown.com/thumb/18286917.jpeg",
            "properlySizedImageURL": "https://media.bandsintown.com/110x110/18286917.webp",
            "callToActionRedirectUrl": "https://www.bandsintown.com/e/106020080-satin-beige-at-patch-chelmsford?came_from=257&utm_medium=web&utm_source=home&utm_campaign=ticket_rsvp",
            "fallbackImageUrl": "https://assets.prod.bandsintown.com/images/homeIcon/festivalPlaceHolderImage/06.png",
            "artistName": "Satin Beige",
            "venueName": "Patch Chelmsford",
            "streamingEvent": false,
            "title": "Ignite Social: Composure",
            "locationText": "Chelmsford, United Kingdom",
            "pinIconSrc": "https://assets.prod.bandsintown.com/images/pinIcon.svg",
            "eventUrl": "https://www.bandsintown.com/e/106020080-satin-beige-at-patch-chelmsford?came_from=257&utm_medium=web&utm_source=home&utm_campaign=event",
            "artistUrl": "https://www.bandsintown.com/a/6368522-satin-beige?came_from=257&utm_medium=web&utm_source=home&utm_campaign=event",
            "watchLiveText": "Watch Live",
            "isPlus": false,
            "callToActionText": "Tickets & RSVP",
            "rsvpCount": "0",
            "rsvpCountInt": 0,
            "startsAt": "2024-10-10T19:00:00",
            "endsAt": "2024-10-10T22:00:00",
            "timezone": "Europe/London",
            "displayRule": "datetime",
            "locale": "en"
        },
        {
            "artistImageSrc": "https://photos.bandsintown.com/thumb/9368299.jpeg",
            "properlySizedImageURL": "https://media.bandsintown.com/110x110/9368299.webp",
            "callToActionRedirectUrl": "https://www.bandsintown.com/e/1030000924-catherine-bohart-at-bloomsbury-theatre-and-studio?came_from=257&utm_medium=web&utm_source=home&utm_campaign=ticket_rsvp",
            "fallbackImageUrl": "https://assets.prod.bandsintown.com/images/homeIcon/festivalPlaceHolderImage/01.png",
            "artistName": "Catherine Bohart",
            "venueName": "Bloomsbury Theatre and Studio",
            "streamingEvent": false,
            "title": null,
            "locationText": "London, United Kingdom",
            "pinIconSrc": "https://assets.prod.bandsintown.com/images/pinIcon.svg",
            "eventUrl": "https://www.bandsintown.com/e/1030000924-catherine-bohart-at-bloomsbury-theatre-and-studio?came_from=257&utm_medium=web&utm_source=home&utm_campaign=event",
            "artistUrl": "https://www.bandsintown.com/a/15110289-catherine-bohart?came_from=257&utm_medium=web&utm_source=home&utm_campaign=event",
            "watchLiveText": "Watch Live",
            "isPlus": false,
            "callToActionText": "Tickets & RSVP",
            "rsvpCount": "3",
            "rsvpCountInt": 3,
            "startsAt": "2024-10-10T19:00:00",
            "timezone": "Europe/London",
            "displayRule": "datetime",
            "locale": "en"
        },
        {
            "artistImageSrc": "https://photos.bandsintown.com/thumb/18244989.jpeg",
            "properlySizedImageURL": "https://media.bandsintown.com/110x110/18244989.webp",
            "callToActionRedirectUrl": "https://www.bandsintown.com/e/105961642-the-vanns-at-two-palms?came_from=257&utm_medium=web&utm_source=home&utm_campaign=ticket_rsvp",
            "fallbackImageUrl": "https://assets.prod.bandsintown.com/images/homeIcon/festivalPlaceHolderImage/07.png",
            "artistName": "The VANNS",
            "venueName": "TWO PALMS",
            "streamingEvent": false,
            "title": "The VANNS @ Two Palms, London",
            "locationText": "London, United Kingdom",
            "pinIconSrc": "https://assets.prod.bandsintown.com/images/pinIcon.svg",
            "eventUrl": "https://www.bandsintown.com/e/105961642-the-vanns-at-two-palms?came_from=257&utm_medium=web&utm_source=home&utm_campaign=event",
            "artistUrl": "https://www.bandsintown.com/a/2690456-the-vanns?came_from=257&utm_medium=web&utm_source=home&utm_campaign=event",
            "watchLiveText": "Watch Live",
            "isPlus": false,
            "callToActionText": "Tickets & RSVP",
            "rsvpCount": "12",
            "rsvpCountInt": 12,
            "startsAt": "2024-10-10T19:00:00",
            "timezone": "Europe/London",
            "displayRule": "datetime",
            "locale": "en"
        },
        {
            "artistImageSrc": "https://photos.bandsintown.com/thumb/18298182.jpeg",
            "properlySizedImageURL": "https://media.bandsintown.com/110x110/18298182.webp",
            "callToActionRedirectUrl": "https://www.bandsintown.com/e/105975907-georgia-nevada-at-hot-box-live?came_from=257&utm_medium=web&utm_source=home&utm_campaign=ticket_rsvp",
            "fallbackImageUrl": "https://assets.prod.bandsintown.com/images/homeIcon/festivalPlaceHolderImage/03.png",
            "artistName": "Georgia Nevada",
            "venueName": "Hot Box Live",
            "streamingEvent": false,
            "title": "Georgia Nevada supporting Louise Parker ",
            "locationText": "Chelmsford, United Kingdom",
            "pinIconSrc": "https://assets.prod.bandsintown.com/images/pinIcon.svg",
            "eventUrl": "https://www.bandsintown.com/e/105975907-georgia-nevada-at-hot-box-live?came_from=257&utm_medium=web&utm_source=home&utm_campaign=event",
            "artistUrl": "https://www.bandsintown.com/a/11509445-georgia-nevada?came_from=257&utm_medium=web&utm_source=home&utm_campaign=event",
            "watchLiveText": "Watch Live",
            "isPlus": false,
            "callToActionText": "Tickets & RSVP",
            "rsvpCount": "1",
            "rsvpCountInt": 1,
            "startsAt": "2024-10-10T19:00:00",
            "timezone": "Europe/London",
            "displayRule": "datetime",
            "locale": "en"
        },
        {
            "artistImageSrc": "https://photos.bandsintown.com/thumb/17320909.jpeg",
            "properlySizedImageURL": "https://media.bandsintown.com/110x110/17320909.webp",
            "callToActionRedirectUrl": "https://www.bandsintown.com/e/105624942-giant-walker-at-the-sussex-arms?came_from=257&utm_medium=web&utm_source=home&utm_campaign=ticket_rsvp",
            "fallbackImageUrl": "https://assets.prod.bandsintown.com/images/homeIcon/festivalPlaceHolderImage/07.png",
            "artistName": "Giant Walker",
            "venueName": "The Sussex Arms",
            "streamingEvent": false,
            "title": "Tunbridge Wells",
            "locationText": "Royal Tunbridge Wells, United Kingdom",
            "pinIconSrc": "https://assets.prod.bandsintown.com/images/pinIcon.svg",
            "eventUrl": "https://www.bandsintown.com/e/105624942-giant-walker-at-the-sussex-arms?came_from=257&utm_medium=web&utm_source=home&utm_campaign=event",
            "artistUrl": "https://www.bandsintown.com/a/15541289-giant-walker?came_from=257&utm_medium=web&utm_source=home&utm_campaign=event",
            "watchLiveText": "Watch Live",
            "isPlus": false,
            "callToActionText": "Tickets & RSVP",
            "rsvpCount": "6",
            "rsvpCountInt": 6,
            "startsAt": "2024-10-10T19:00:00",
            "timezone": "Europe/London",
            "displayRule": "datetime",
            "locale": "en"
        },
        {
            "artistImageSrc": "https://photos.bandsintown.com/thumb/15826635.jpeg",
            "properlySizedImageURL": "https://media.bandsintown.com/110x110/15826635.webp",
            "callToActionRedirectUrl": "https://www.bandsintown.com/e/105563469-youngr-at-the-steel-yard?came_from=257&utm_medium=web&utm_source=home&utm_campaign=ticket_rsvp",
            "fallbackImageUrl": "https://assets.prod.bandsintown.com/images/homeIcon/festivalPlaceHolderImage/05.png",
            "artistName": "Youngr",
            "venueName": "The Steel Yard",
            "streamingEvent": false,
            "title": null,
            "locationText": "London, United Kingdom",
            "pinIconSrc": "https://assets.prod.bandsintown.com/images/pinIcon.svg",
            "eventUrl": "https://www.bandsintown.com/e/105563469-youngr-at-the-steel-yard?came_from=257&utm_medium=web&utm_source=home&utm_campaign=event",
            "artistUrl": "https://www.bandsintown.com/a/4691473-youngr?came_from=257&utm_medium=web&utm_source=home&utm_campaign=event",
            "watchLiveText": "Watch Live",
            "isPlus": false,
            "callToActionText": "Tickets & RSVP",
            "rsvpCount": "29",
            "rsvpCountInt": 29,
            "startsAt": "2024-10-10T19:00:00",
            "timezone": "Europe/London",
            "displayRule": "datetime",
            "locale": "en"
        },
        {
            "artistImageSrc": "https://photos.bandsintown.com/thumb/254230.jpeg",
            "properlySizedImageURL": "https://media.bandsintown.com/110x110/254230.webp",
            "callToActionRedirectUrl": "https://www.bandsintown.com/e/1032810336-bull-at-signature-brew-haggerston?came_from=257&utm_medium=web&utm_source=home&utm_campaign=ticket_rsvp",
            "fallbackImageUrl": "https://assets.prod.bandsintown.com/images/homeIcon/festivalPlaceHolderImage/01.png",
            "artistName": "Bull",
            "venueName": "Signature Brew Haggerston",
            "streamingEvent": false,
            "title": null,
            "locationText": "Haggerston, United Kingdom",
            "pinIconSrc": "https://assets.prod.bandsintown.com/images/pinIcon.svg",
            "eventUrl": "https://www.bandsintown.com/e/1032810336-bull-at-signature-brew-haggerston?came_from=257&utm_medium=web&utm_source=home&utm_campaign=event",
            "artistUrl": "https://www.bandsintown.com/a/645653-bull?came_from=257&utm_medium=web&utm_source=home&utm_campaign=event",
            "watchLiveText": "Watch Live",
            "isPlus": false,
            "callToActionText": "Tickets & RSVP",
            "rsvpCount": "2",
            "rsvpCountInt": 2,
            "startsAt": "2024-10-10T19:00:00",
            "timezone": "Europe/London",
            "displayRule": "datetime",
            "locale": "en"
        },
        {
            "artistImageSrc": "https://photos.bandsintown.com/thumb/6312700.jpeg",
            "properlySizedImageURL": "https://media.bandsintown.com/110x110/6312700.webp",
            "callToActionRedirectUrl": "https://www.bandsintown.com/e/1032628528-stratos-at-grow?came_from=257&utm_medium=web&utm_source=home&utm_campaign=ticket_rsvp",
            "fallbackImageUrl": "https://assets.prod.bandsintown.com/images/homeIcon/festivalPlaceHolderImage/08.png",
            "artistName": "Stratos",
            "venueName": "Grow",
            "streamingEvent": false,
            "title": null,
            "locationText": "London, United Kingdom",
            "pinIconSrc": "https://assets.prod.bandsintown.com/images/pinIcon.svg",
            "eventUrl": "https://www.bandsintown.com/e/1032628528-stratos-at-grow?came_from=257&utm_medium=web&utm_source=home&utm_campaign=event",
            "artistUrl": "https://www.bandsintown.com/a/807633-stratos?came_from=257&utm_medium=web&utm_source=home&utm_campaign=event",
            "watchLiveText": "Watch Live",
            "isPlus": false,
            "callToActionText": "Tickets & RSVP",
            "rsvpCount": "0",
            "rsvpCountInt": 0,
            "startsAt": "2024-10-10T19:00:00",
            "timezone": "Europe/London",
            "displayRule": "datetime",
            "locale": "en"
        },
        {
            "artistImageSrc": "https://assets.prod.bandsintown.com/images/homeIcon/festivalPlaceHolderImage/08.png",
            "properlySizedImageURL": "https://assets.prod.bandsintown.com/images/homeIcon/festivalPlaceHolderImage/08.webp",
            "callToActionRedirectUrl": "https://www.bandsintown.com/e/1033023755-jim-lockey-and-the-solemn-sun-at-oslo-hackney?came_from=257&utm_medium=web&utm_source=home&utm_campaign=ticket_rsvp",
            "fallbackImageUrl": "https://assets.prod.bandsintown.com/images/homeIcon/festivalPlaceHolderImage/06.png",
            "artistName": "Jim Lockey and the Solemn Sun",
            "venueName": "Oslo Hackney",
            "streamingEvent": false,
            "title": null,
            "locationText": "London, United Kingdom",
            "pinIconSrc": "https://assets.prod.bandsintown.com/images/pinIcon.svg",
            "eventUrl": "https://www.bandsintown.com/e/1033023755-jim-lockey-and-the-solemn-sun-at-oslo-hackney?came_from=257&utm_medium=web&utm_source=home&utm_campaign=event",
            "artistUrl": "https://www.bandsintown.com/a/975894-jim-lockey-and-the-solemn-sun?came_from=257&utm_medium=web&utm_source=home&utm_campaign=event",
            "watchLiveText": "Watch Live",
            "isPlus": false,
            "callToActionText": "Tickets & RSVP",
            "rsvpCount": "0",
            "rsvpCountInt": 0,
            "startsAt": "2024-10-10T19:00:00",
            "timezone": "Europe/London",
            "displayRule": "datetime",
            "locale": "en"
        },
        {
            "artistImageSrc": "https://photos.bandsintown.com/thumb/17162332.jpeg",
            "properlySizedImageURL": "https://media.bandsintown.com/110x110/17162332.webp",
            "callToActionRedirectUrl": "https://www.bandsintown.com/e/105548792-mimi-barks-at-the-camden-assembly?came_from=257&utm_medium=web&utm_source=home&utm_campaign=ticket_rsvp",
            "fallbackImageUrl": "https://assets.prod.bandsintown.com/images/homeIcon/festivalPlaceHolderImage/01.png",
            "artistName": "Mimi Barks",
            "venueName": "The Camden Assembly",
            "streamingEvent": false,
            "title": "Mimi Barks - THIS IS DOOM TRAP tour ",
            "locationText": "London, United Kingdom",
            "pinIconSrc": "https://assets.prod.bandsintown.com/images/pinIcon.svg",
            "eventUrl": "https://www.bandsintown.com/e/105548792-mimi-barks-at-the-camden-assembly?came_from=257&utm_medium=web&utm_source=home&utm_campaign=event",
            "artistUrl": "https://www.bandsintown.com/a/15491412-mimi-barks?came_from=257&utm_medium=web&utm_source=home&utm_campaign=event",
            "watchLiveText": "Watch Live",
            "isPlus": false,
            "callToActionText": "Tickets & RSVP",
            "rsvpCount": "9",
            "rsvpCountInt": 9,
            "startsAt": "2024-10-10T19:00:00",
            "timezone": "Europe/London",
            "displayRule": "datetime",
            "locale": "en"
        },
        {
            "artistImageSrc": "https://photos.bandsintown.com/thumb/9619256.jpeg",
            "properlySizedImageURL": "https://media.bandsintown.com/110x110/9619256.webp",
            "callToActionRedirectUrl": "https://www.bandsintown.com/e/1031122143-jimmy-carr-at-g-live-guildford?came_from=257&utm_medium=web&utm_source=home&utm_campaign=ticket_rsvp",
            "fallbackImageUrl": "https://assets.prod.bandsintown.com/images/homeIcon/festivalPlaceHolderImage/02.png",
            "artistName": "Jimmy Carr",
            "venueName": "G Live Guildford",
            "streamingEvent": false,
            "title": null,
            "locationText": "Guildford, United Kingdom",
            "pinIconSrc": "https://assets.prod.bandsintown.com/images/pinIcon.svg",
            "eventUrl": "https://www.bandsintown.com/e/1031122143-jimmy-carr-at-g-live-guildford?came_from=257&utm_medium=web&utm_source=home&utm_campaign=event",
            "artistUrl": "https://www.bandsintown.com/a/49816-jimmy-carr?came_from=257&utm_medium=web&utm_source=home&utm_campaign=event",
            "watchLiveText": "Watch Live",
            "isPlus": false,
            "callToActionText": "Tickets & RSVP",
            "rsvpCount": "15",
            "rsvpCountInt": 15,
            "startsAt": "2024-10-10T19:00:00",
            "timezone": "Europe/London",
            "displayRule": "datetime",
            "locale": "en"
        },
        {
            "artistImageSrc": "https://photos.bandsintown.com/thumb/15758277.jpeg",
            "properlySizedImageURL": "https://media.bandsintown.com/110x110/15758277.webp",
            "callToActionRedirectUrl": "https://www.bandsintown.com/e/1032384997-stellvris-at-229?came_from=257&utm_medium=web&utm_source=home&utm_campaign=ticket_rsvp",
            "fallbackImageUrl": "https://assets.prod.bandsintown.com/images/homeIcon/festivalPlaceHolderImage/08.png",
            "artistName": "STELLVRIS",
            "venueName": "229",
            "streamingEvent": false,
            "title": null,
            "locationText": "London, United Kingdom",
            "pinIconSrc": "https://assets.prod.bandsintown.com/images/pinIcon.svg",
            "eventUrl": "https://www.bandsintown.com/e/1032384997-stellvris-at-229?came_from=257&utm_medium=web&utm_source=home&utm_campaign=event",
            "artistUrl": "https://www.bandsintown.com/a/15528581-stellvris?came_from=257&utm_medium=web&utm_source=home&utm_campaign=event",
            "watchLiveText": "Watch Live",
            "isPlus": false,
            "callToActionText": "Tickets & RSVP",
            "rsvpCount": "3",
            "rsvpCountInt": 3,
            "startsAt": "2024-10-10T19:00:00",
            "timezone": "Europe/London",
            "displayRule": "datetime",
            "locale": "en"
        },
        {
            "artistImageSrc": "https://assets.prod.bandsintown.com/images/homeIcon/festivalPlaceHolderImage/02.png",
            "properlySizedImageURL": "https://assets.prod.bandsintown.com/images/homeIcon/festivalPlaceHolderImage/05.webp",
            "callToActionRedirectUrl": "https://www.bandsintown.com/e/1033026116-jim-lockey-and-the-solemn-sun-at-oslo-hackney?came_from=257&utm_medium=web&utm_source=home&utm_campaign=ticket_rsvp",
            "fallbackImageUrl": "https://assets.prod.bandsintown.com/images/homeIcon/festivalPlaceHolderImage/01.png",
            "artistName": "Jim Lockey & the Solemn Sun",
            "venueName": "Oslo Hackney",
            "streamingEvent": false,
            "title": null,
            "locationText": "London, United Kingdom",
            "pinIconSrc": "https://assets.prod.bandsintown.com/images/pinIcon.svg",
            "eventUrl": "https://www.bandsintown.com/e/1033026116-jim-lockey-and-the-solemn-sun-at-oslo-hackney?came_from=257&utm_medium=web&utm_source=home&utm_campaign=event",
            "artistUrl": "https://www.bandsintown.com/a/1127132-jim-lockey-and-the-solemn-sun?came_from=257&utm_medium=web&utm_source=home&utm_campaign=event",
            "watchLiveText": "Watch Live",
            "isPlus": false,
            "callToActionText": "Tickets & RSVP",
            "rsvpCount": "1",
            "rsvpCountInt": 1,
            "startsAt": "2024-10-10T19:00:00",
            "timezone": "Europe/London",
            "displayRule": "datetime",
            "locale": "en"
        },
        {
            "artistImageSrc": "https://photos.bandsintown.com/thumb/295038.jpeg",
            "properlySizedImageURL": "https://media.bandsintown.com/110x110/295038.webp",
            "callToActionRedirectUrl": "https://www.bandsintown.com/e/1032715017-lonyo-at-boisdale-of-canary-wharf?came_from=257&utm_medium=web&utm_source=home&utm_campaign=ticket_rsvp",
            "fallbackImageUrl": "https://assets.prod.bandsintown.com/images/homeIcon/festivalPlaceHolderImage/04.png",
            "artistName": "Lonyo",
            "venueName": "Boisdale of Canary Wharf",
            "streamingEvent": false,
            "title": null,
            "locationText": "London, United Kingdom",
            "pinIconSrc": "https://assets.prod.bandsintown.com/images/pinIcon.svg",
            "eventUrl": "https://www.bandsintown.com/e/1032715017-lonyo-at-boisdale-of-canary-wharf?came_from=257&utm_medium=web&utm_source=home&utm_campaign=event",
            "artistUrl": "https://www.bandsintown.com/a/115945-lonyo?came_from=257&utm_medium=web&utm_source=home&utm_campaign=event",
            "watchLiveText": "Watch Live",
            "isPlus": false,
            "callToActionText": "Tickets & RSVP",
            "rsvpCount": "0",
            "rsvpCountInt": 0,
            "startsAt": "2024-10-10T19:00:00",
            "timezone": "Europe/London",
            "displayRule": "datetime",
            "locale": "en"
        },
        {
            "artistImageSrc": "https://assets.prod.bandsintown.com/images/homeIcon/festivalPlaceHolderImage/07.png",
            "properlySizedImageURL": "https://assets.prod.bandsintown.com/images/homeIcon/festivalPlaceHolderImage/03.webp",
            "callToActionRedirectUrl": "https://www.bandsintown.com/e/105427167-look-mum-no-computer-at-rich-mix?came_from=257&utm_medium=web&utm_source=home&utm_campaign=ticket_rsvp",
            "fallbackImageUrl": "https://assets.prod.bandsintown.com/images/homeIcon/festivalPlaceHolderImage/03.png",
            "artistName": "LOOK MUM NO COMPUTER",
            "venueName": "Rich Mix",
            "streamingEvent": false,
            "title": null,
            "locationText": "London, United Kingdom",
            "pinIconSrc": "https://assets.prod.bandsintown.com/images/pinIcon.svg",
            "eventUrl": "https://www.bandsintown.com/e/105427167-look-mum-no-computer-at-rich-mix?came_from=257&utm_medium=web&utm_source=home&utm_campaign=event",
            "artistUrl": "https://www.bandsintown.com/a/14164978-look-mum-no-computer?came_from=257&utm_medium=web&utm_source=home&utm_campaign=event",
            "watchLiveText": "Watch Live",
            "isPlus": false,
            "callToActionText": "Tickets & RSVP",
            "rsvpCount": "10",
            "rsvpCountInt": 10,
            "startsAt": "2024-10-10T19:00:00",
            "timezone": "Europe/London",
            "displayRule": "datetime",
            "locale": "en"
        },
        {
            "artistImageSrc": "https://photos.bandsintown.com/thumb/6039696.jpeg",
            "properlySizedImageURL": "https://media.bandsintown.com/110x110/6039696.webp",
            "callToActionRedirectUrl": "https://www.bandsintown.com/e/1033027760-magnolia-at-dream-bags-jaguar-shoes-shoreditch?came_from=257&utm_medium=web&utm_source=home&utm_campaign=ticket_rsvp",
            "fallbackImageUrl": "https://assets.prod.bandsintown.com/images/homeIcon/festivalPlaceHolderImage/03.png",
            "artistName": "Magnolia",
            "venueName": "Dream Bags Jaguar Shoes Shoreditch",
            "streamingEvent": false,
            "title": null,
            "locationText": "London, United Kingdom",
            "pinIconSrc": "https://assets.prod.bandsintown.com/images/pinIcon.svg",
            "eventUrl": "https://www.bandsintown.com/e/1033027760-magnolia-at-dream-bags-jaguar-shoes-shoreditch?came_from=257&utm_medium=web&utm_source=home&utm_campaign=event",
            "artistUrl": "https://www.bandsintown.com/a/17872-magnolia?came_from=257&utm_medium=web&utm_source=home&utm_campaign=event",
            "watchLiveText": "Watch Live",
            "isPlus": false,
            "callToActionText": "Tickets & RSVP",
            "rsvpCount": "0",
            "rsvpCountInt": 0,
            "startsAt": "2024-10-10T19:00:00",
            "timezone": "Europe/London",
            "displayRule": "datetime",
            "locale": "en"
        },
        {
            "artistImageSrc": "https://photos.bandsintown.com/thumb/17217107.jpeg",
            "properlySizedImageURL": "https://media.bandsintown.com/110x110/17217107.webp",
            "callToActionRedirectUrl": "https://www.bandsintown.com/e/1031870413-anna-pancaldi-at-the-lexington?came_from=257&utm_medium=web&utm_source=home&utm_campaign=ticket_rsvp",
            "fallbackImageUrl": "https://assets.prod.bandsintown.com/images/homeIcon/festivalPlaceHolderImage/06.png",
            "artistName": "Anna Pancaldi",
            "venueName": "The Lexington",
            "streamingEvent": false,
            "title": "Anna Pancaldi live in LONDON (FULL BAND show)",
            "locationText": "London, United Kingdom",
            "pinIconSrc": "https://assets.prod.bandsintown.com/images/pinIcon.svg",
            "eventUrl": "https://www.bandsintown.com/e/1031870413-anna-pancaldi-at-the-lexington?came_from=257&utm_medium=web&utm_source=home&utm_campaign=event",
            "artistUrl": "https://www.bandsintown.com/a/3766302-anna-pancaldi?came_from=257&utm_medium=web&utm_source=home&utm_campaign=event",
            "watchLiveText": "Watch Live",
            "isPlus": false,
            "callToActionText": "Tickets & RSVP",
            "rsvpCount": "2",
            "rsvpCountInt": 2,
            "startsAt": "2024-10-10T19:00:00",
            "timezone": "Europe/London",
            "displayRule": "datetime",
            "locale": "en"
        },
        {
            "artistImageSrc": "https://photos.bandsintown.com/thumb/14628442.jpeg",
            "properlySizedImageURL": "https://media.bandsintown.com/110x110/14628442.webp",
            "callToActionRedirectUrl": "https://www.bandsintown.com/e/1032655278-tertia-at-sebright-arms?came_from=257&utm_medium=web&utm_source=home&utm_campaign=ticket_rsvp",
            "fallbackImageUrl": "https://assets.prod.bandsintown.com/images/homeIcon/festivalPlaceHolderImage/08.png",
            "artistName": "TERTIA",
            "venueName": "Sebright Arms",
            "streamingEvent": false,
            "title": null,
            "locationText": "London, United Kingdom",
            "pinIconSrc": "https://assets.prod.bandsintown.com/images/pinIcon.svg",
            "eventUrl": "https://www.bandsintown.com/e/1032655278-tertia-at-sebright-arms?came_from=257&utm_medium=web&utm_source=home&utm_campaign=event",
            "artistUrl": "https://www.bandsintown.com/a/1816071-tertia?came_from=257&utm_medium=web&utm_source=home&utm_campaign=event",
            "watchLiveText": "Watch Live",
            "isPlus": false,
            "callToActionText": "Tickets & RSVP",
            "rsvpCount": "2",
            "rsvpCountInt": 2,
            "startsAt": "2024-10-10T19:00:00",
            "timezone": "Europe/London",
            "displayRule": "datetime",
            "locale": "en"
        },
        {
            "artistImageSrc": "https://photos.bandsintown.com/thumb/17064886.jpeg",
            "properlySizedImageURL": "https://media.bandsintown.com/110x110/17064886.webp",
            "callToActionRedirectUrl": "https://www.bandsintown.com/e/105288875-benoit-viellefon-at-the-brunswick?came_from=257&utm_medium=web&utm_source=home&utm_campaign=ticket_rsvp",
            "fallbackImageUrl": "https://assets.prod.bandsintown.com/images/homeIcon/festivalPlaceHolderImage/06.png",
            "artistName": "Benoit Viellefon",
            "venueName": "The Brunswick",
            "streamingEvent": false,
            "title": null,
            "locationText": "Hove, United Kingdom",
            "pinIconSrc": "https://assets.prod.bandsintown.com/images/pinIcon.svg",
            "eventUrl": "https://www.bandsintown.com/e/105288875-benoit-viellefon-at-the-brunswick?came_from=257&utm_medium=web&utm_source=home&utm_campaign=event",
            "artistUrl": "https://www.bandsintown.com/a/1040151-benoit-viellefon?came_from=257&utm_medium=web&utm_source=home&utm_campaign=event",
            "watchLiveText": "Watch Live",
            "isPlus": false,
            "callToActionText": "Tickets & RSVP",
            "rsvpCount": "4",
            "rsvpCountInt": 4,
            "startsAt": "2024-10-10T19:00:00",
            "endsAt": "2024-10-10T22:00:00",
            "timezone": "Europe/London",
            "displayRule": "datetime",
            "locale": "en"
        },
        {
            "artistImageSrc": "https://assets.prod.bandsintown.com/images/homeIcon/festivalPlaceHolderImage/06.png",
            "properlySizedImageURL": "https://assets.prod.bandsintown.com/images/homeIcon/festivalPlaceHolderImage/03.webp",
            "callToActionRedirectUrl": "https://www.bandsintown.com/e/1033134643-unorthadox-at-the-finsbury?came_from=257&utm_medium=web&utm_source=home&utm_campaign=ticket_rsvp",
            "fallbackImageUrl": "https://assets.prod.bandsintown.com/images/homeIcon/festivalPlaceHolderImage/07.png",
            "artistName": "Unorthadox",
            "venueName": "The Finsbury",
            "streamingEvent": false,
            "title": null,
            "locationText": "London, United Kingdom",
            "pinIconSrc": "https://assets.prod.bandsintown.com/images/pinIcon.svg",
            "eventUrl": "https://www.bandsintown.com/e/1033134643-unorthadox-at-the-finsbury?came_from=257&utm_medium=web&utm_source=home&utm_campaign=event",
            "artistUrl": "https://www.bandsintown.com/a/405813-unorthadox?came_from=257&utm_medium=web&utm_source=home&utm_campaign=event",
            "watchLiveText": "Watch Live",
            "isPlus": false,
            "callToActionText": "Tickets & RSVP",
            "rsvpCount": "1",
            "rsvpCountInt": 1,
            "startsAt": "2024-10-10T19:00:00",
            "timezone": "Europe/London",
            "displayRule": "datetime",
            "locale": "en"
        },
        {
            "artistImageSrc": "https://assets.prod.bandsintown.com/images/homeIcon/festivalPlaceHolderImage/06.png",
            "properlySizedImageURL": "https://assets.prod.bandsintown.com/images/homeIcon/festivalPlaceHolderImage/05.webp",
            "callToActionRedirectUrl": "https://www.bandsintown.com/e/1032463490-fruko-at-electric-brixton?came_from=257&utm_medium=web&utm_source=home&utm_campaign=ticket_rsvp",
            "fallbackImageUrl": "https://assets.prod.bandsintown.com/images/homeIcon/festivalPlaceHolderImage/06.png",
            "artistName": "Fruko",
            "venueName": "Electric Brixton",
            "streamingEvent": false,
            "title": null,
            "locationText": "London, United Kingdom",
            "pinIconSrc": "https://assets.prod.bandsintown.com/images/pinIcon.svg",
            "eventUrl": "https://www.bandsintown.com/e/1032463490-fruko-at-electric-brixton?came_from=257&utm_medium=web&utm_source=home&utm_campaign=event",
            "artistUrl": "https://www.bandsintown.com/a/371567-fruko?came_from=257&utm_medium=web&utm_source=home&utm_campaign=event",
            "watchLiveText": "Watch Live",
            "isPlus": false,
            "callToActionText": "Tickets & RSVP",
            "rsvpCount": "1",
            "rsvpCountInt": 1,
            "startsAt": "2024-10-10T19:00:00",
            "timezone": "Europe/London",
            "displayRule": "datetime",
            "locale": "en"
        },
        {
            "artistImageSrc": "https://photos.bandsintown.com/thumb/17987863.jpeg",
            "properlySizedImageURL": "https://media.bandsintown.com/110x110/17987863.webp",
            "callToActionRedirectUrl": "https://www.bandsintown.com/e/105878158-stormborn-at-cart-and-horses?came_from=257&utm_medium=web&utm_source=home&utm_campaign=ticket_rsvp",
            "fallbackImageUrl": "https://assets.prod.bandsintown.com/images/homeIcon/festivalPlaceHolderImage/05.png",
            "artistName": "Stormborn",
            "venueName": "Cart & Horses",
            "streamingEvent": false,
            "title": "STORMBORN, LYCANTHRO, PRIMITAI @ Cart & Horses",
            "locationText": "London, United Kingdom",
            "pinIconSrc": "https://assets.prod.bandsintown.com/images/pinIcon.svg",
            "eventUrl": "https://www.bandsintown.com/e/105878158-stormborn-at-cart-and-horses?came_from=257&utm_medium=web&utm_source=home&utm_campaign=event",
            "artistUrl": "https://www.bandsintown.com/a/1158526-stormborn?came_from=257&utm_medium=web&utm_source=home&utm_campaign=event",
            "watchLiveText": "Watch Live",
            "isPlus": false,
            "callToActionText": "Tickets & RSVP",
            "rsvpCount": "0",
            "rsvpCountInt": 0,
            "startsAt": "2024-10-10T19:00:00",
            "endsAt": "2024-10-10T23:30:00",
            "timezone": "Europe/London",
            "displayRule": "datetime",
            "locale": "en"
        },
        {
            "artistImageSrc": "https://photos.bandsintown.com/thumb/8930549.jpeg",
            "properlySizedImageURL": "https://media.bandsintown.com/110x110/8930549.webp",
            "callToActionRedirectUrl": "https://www.bandsintown.com/e/105575123-tre-allegri-ragazzi-morti-at-the-t.e-dingwall-building?came_from=257&utm_medium=web&utm_source=home&utm_campaign=ticket_rsvp",
            "fallbackImageUrl": "https://assets.prod.bandsintown.com/images/homeIcon/festivalPlaceHolderImage/06.png",
            "artistName": "Tre allegri ragazzi morti",
            "venueName": "The T.E Dingwall Building",
            "streamingEvent": false,
            "title": null,
            "locationText": "London, United Kingdom",
            "pinIconSrc": "https://assets.prod.bandsintown.com/images/pinIcon.svg",
            "eventUrl": "https://www.bandsintown.com/e/105575123-tre-allegri-ragazzi-morti-at-the-t.e-dingwall-building?came_from=257&utm_medium=web&utm_source=home&utm_campaign=event",
            "artistUrl": "https://www.bandsintown.com/a/77120-tre-allegri-ragazzi-morti?came_from=257&utm_medium=web&utm_source=home&utm_campaign=event",
            "watchLiveText": "Watch Live",
            "isPlus": false,
            "callToActionText": "Tickets & RSVP",
            "rsvpCount": "21",
            "rsvpCountInt": 21,
            "startsAt": "2024-10-10T19:00:00",
            "timezone": "Europe/London",
            "displayRule": "datetime",
            "locale": "en"
        },
        {
            "artistImageSrc": "https://photos.bandsintown.com/thumb/17770724.jpeg",
            "properlySizedImageURL": "https://media.bandsintown.com/110x110/17770724.webp",
            "callToActionRedirectUrl": "https://www.bandsintown.com/e/105795445-shed-seven-at-pryzm-kingston?came_from=257&utm_medium=web&utm_source=home&utm_campaign=ticket_rsvp",
            "fallbackImageUrl": "https://assets.prod.bandsintown.com/images/homeIcon/festivalPlaceHolderImage/02.png",
            "artistName": "Shed Seven",
            "venueName": "PRYZM Kingston",
            "streamingEvent": false,
            "title": "Change Giver & Hits - Pryzm, Kingston ",
            "locationText": "Kingston upon Thames, United Kingdom",
            "pinIconSrc": "https://assets.prod.bandsintown.com/images/pinIcon.svg",
            "eventUrl": "https://www.bandsintown.com/e/105795445-shed-seven-at-pryzm-kingston?came_from=257&utm_medium=web&utm_source=home&utm_campaign=event",
            "artistUrl": "https://www.bandsintown.com/a/41289-shed-seven?came_from=257&utm_medium=web&utm_source=home&utm_campaign=event",
            "watchLiveText": "Watch Live",
            "isPlus": false,
            "callToActionText": "Tickets & RSVP",
            "rsvpCount": "80",
            "rsvpCountInt": 80,
            "startsAt": "2024-10-10T19:00:00",
            "endsAt": "2024-10-10T23:00:00",
            "timezone": "Europe/London",
            "displayRule": "datetime",
            "locale": "en"
        },
        {
            "artistImageSrc": "https://photos.bandsintown.com/thumb/17898198.jpeg",
            "properlySizedImageURL": "https://media.bandsintown.com/110x110/17898198.webp",
            "callToActionRedirectUrl": "https://www.bandsintown.com/e/105844939-fruko-y-sus-tesos-at-electric-brixton?came_from=257&utm_medium=web&utm_source=home&utm_campaign=ticket_rsvp",
            "fallbackImageUrl": "https://assets.prod.bandsintown.com/images/homeIcon/festivalPlaceHolderImage/08.png",
            "artistName": "Fruko y Sus Tesos",
            "venueName": "Electric Brixton",
            "streamingEvent": false,
            "title": "Fruko y sus Tesos",
            "locationText": "London, United Kingdom",
            "pinIconSrc": "https://assets.prod.bandsintown.com/images/pinIcon.svg",
            "eventUrl": "https://www.bandsintown.com/e/105844939-fruko-y-sus-tesos-at-electric-brixton?came_from=257&utm_medium=web&utm_source=home&utm_campaign=event",
            "artistUrl": "https://www.bandsintown.com/a/58440-fruko-y-sus-tesos?came_from=257&utm_medium=web&utm_source=home&utm_campaign=event",
            "watchLiveText": "Watch Live",
            "isPlus": false,
            "callToActionText": "Tickets & RSVP",
            "rsvpCount": "6",
            "rsvpCountInt": 6,
            "startsAt": "2024-10-10T19:00:00",
            "endsAt": "2024-10-10T23:00:00",
            "timezone": "Europe/London",
            "displayRule": "datetime",
            "locale": "en"
        },
        {
            "artistImageSrc": "https://photos.bandsintown.com/thumb/18416059.jpeg",
            "properlySizedImageURL": "https://media.bandsintown.com/110x110/18416059.webp",
            "callToActionRedirectUrl": "https://www.bandsintown.com/e/106019968-hd-4884-at-the-camden-assembly?came_from=257&utm_medium=web&utm_source=home&utm_campaign=ticket_rsvp",
            "fallbackImageUrl": "https://assets.prod.bandsintown.com/images/homeIcon/festivalPlaceHolderImage/04.png",
            "artistName": "HD-4884",
            "venueName": "The Camden Assembly",
            "streamingEvent": false,
            "title": "Mimi Barks with Raven Gray (Doom Trap Tour)",
            "locationText": "London, United Kingdom",
            "pinIconSrc": "https://assets.prod.bandsintown.com/images/pinIcon.svg",
            "eventUrl": "https://www.bandsintown.com/e/106019968-hd-4884-at-the-camden-assembly?came_from=257&utm_medium=web&utm_source=home&utm_campaign=event",
            "artistUrl": "https://www.bandsintown.com/a/15549252-hd-4884?came_from=257&utm_medium=web&utm_source=home&utm_campaign=event",
            "watchLiveText": "Watch Live",
            "isPlus": false,
            "callToActionText": "Tickets & RSVP",
            "rsvpCount": "0",
            "rsvpCountInt": 0,
            "startsAt": "2024-10-10T19:00:00",
            "timezone": "Europe/London",
            "displayRule": "datetime",
            "locale": "en"
        },
        {
            "artistImageSrc": "https://assets.prod.bandsintown.com/images/homeIcon/festivalPlaceHolderImage/01.png",
            "properlySizedImageURL": "https://assets.prod.bandsintown.com/images/homeIcon/festivalPlaceHolderImage/06.webp",
            "callToActionRedirectUrl": "https://www.bandsintown.com/e/1032959303-matic-horns-at-fox-and-firkin?came_from=257&utm_medium=web&utm_source=home&utm_campaign=ticket_rsvp",
            "fallbackImageUrl": "https://assets.prod.bandsintown.com/images/homeIcon/festivalPlaceHolderImage/03.png",
            "artistName": "Matic Horns",
            "venueName": "Fox & Firkin",
            "streamingEvent": false,
            "title": null,
            "locationText": "London, United Kingdom",
            "pinIconSrc": "https://assets.prod.bandsintown.com/images/pinIcon.svg",
            "eventUrl": "https://www.bandsintown.com/e/1032959303-matic-horns-at-fox-and-firkin?came_from=257&utm_medium=web&utm_source=home&utm_campaign=event",
            "artistUrl": "https://www.bandsintown.com/a/441069-matic-horns?came_from=257&utm_medium=web&utm_source=home&utm_campaign=event",
            "watchLiveText": "Watch Live",
            "isPlus": false,
            "callToActionText": "Tickets & RSVP",
            "rsvpCount": "0",
            "rsvpCountInt": 0,
            "startsAt": "2024-10-10T19:00:00",
            "timezone": "Europe/London",
            "displayRule": "datetime",
            "locale": "en"
        },
        {
            "artistImageSrc": "https://photos.bandsintown.com/thumb/267013.jpeg",
            "properlySizedImageURL": "https://media.bandsintown.com/110x110/267013.webp",
            "callToActionRedirectUrl": "https://www.bandsintown.com/e/1032959299-winston-francis-at-fox-and-firkin?came_from=257&utm_medium=web&utm_source=home&utm_campaign=ticket_rsvp",
            "fallbackImageUrl": "https://assets.prod.bandsintown.com/images/homeIcon/festivalPlaceHolderImage/02.png",
            "artistName": "Winston Francis",
            "venueName": "Fox & Firkin",
            "streamingEvent": false,
            "title": null,
            "locationText": "London, United Kingdom",
            "pinIconSrc": "https://assets.prod.bandsintown.com/images/pinIcon.svg",
            "eventUrl": "https://www.bandsintown.com/e/1032959299-winston-francis-at-fox-and-firkin?came_from=257&utm_medium=web&utm_source=home&utm_campaign=event",
            "artistUrl": "https://www.bandsintown.com/a/83673-winston-francis?came_from=257&utm_medium=web&utm_source=home&utm_campaign=event",
            "watchLiveText": "Watch Live",
            "isPlus": false,
            "callToActionText": "Tickets & RSVP",
            "rsvpCount": "0",
            "rsvpCountInt": 0,
            "startsAt": "2024-10-10T19:00:00",
            "timezone": "Europe/London",
            "displayRule": "datetime",
            "locale": "en"
        },
        {
            "artistImageSrc": "https://photos.bandsintown.com/thumb/260487.jpeg",
            "properlySizedImageURL": "https://media.bandsintown.com/110x110/260487.webp",
            "callToActionRedirectUrl": "https://www.bandsintown.com/e/1032959273-winston-reedy-at-fox-and-firkin?came_from=257&utm_medium=web&utm_source=home&utm_campaign=ticket_rsvp",
            "fallbackImageUrl": "https://assets.prod.bandsintown.com/images/homeIcon/festivalPlaceHolderImage/02.png",
            "artistName": "Winston Reedy",
            "venueName": "Fox & Firkin",
            "streamingEvent": false,
            "title": null,
            "locationText": "London, United Kingdom",
            "pinIconSrc": "https://assets.prod.bandsintown.com/images/pinIcon.svg",
            "eventUrl": "https://www.bandsintown.com/e/1032959273-winston-reedy-at-fox-and-firkin?came_from=257&utm_medium=web&utm_source=home&utm_campaign=event",
            "artistUrl": "https://www.bandsintown.com/a/346253-winston-reedy?came_from=257&utm_medium=web&utm_source=home&utm_campaign=event",
            "watchLiveText": "Watch Live",
            "isPlus": false,
            "callToActionText": "Tickets & RSVP",
            "rsvpCount": "1",
            "rsvpCountInt": 1,
            "startsAt": "2024-10-10T19:00:00",
            "timezone": "Europe/London",
            "displayRule": "datetime",
            "locale": "en"
        },
        {
            "artistImageSrc": "https://photos.bandsintown.com/thumb/11652043.jpeg",
            "properlySizedImageURL": "https://media.bandsintown.com/110x110/11652043.webp",
            "callToActionRedirectUrl": "https://www.bandsintown.com/e/1032682991-highschool-at-o2-academy-brixton?came_from=257&utm_medium=web&utm_source=home&utm_campaign=ticket_rsvp",
            "fallbackImageUrl": "https://assets.prod.bandsintown.com/images/homeIcon/festivalPlaceHolderImage/08.png",
            "artistName": "HighSchool",
            "venueName": "O2 Academy Brixton",
            "streamingEvent": false,
            "title": null,
            "locationText": "London, United Kingdom",
            "pinIconSrc": "https://assets.prod.bandsintown.com/images/pinIcon.svg",
            "eventUrl": "https://www.bandsintown.com/e/1032682991-highschool-at-o2-academy-brixton?came_from=257&utm_medium=web&utm_source=home&utm_campaign=event",
            "artistUrl": "https://www.bandsintown.com/a/15492946-highschool?came_from=257&utm_medium=web&utm_source=home&utm_campaign=event",
            "watchLiveText": "Watch Live",
            "isPlus": false,
            "callToActionText": "Tickets & RSVP",
            "rsvpCount": "4",
            "rsvpCountInt": 4,
            "startsAt": "2024-10-10T19:00:00",
            "timezone": "Europe/London",
            "displayRule": "datetime",
            "locale": "en"
        },
        {
            "artistImageSrc": "https://assets.prod.bandsintown.com/images/homeIcon/festivalPlaceHolderImage/08.png",
            "properlySizedImageURL": "https://assets.prod.bandsintown.com/images/homeIcon/festivalPlaceHolderImage/08.webp",
            "callToActionRedirectUrl": "https://www.bandsintown.com/e/1032959461-mafia-and-fluxy-at-fox-and-firkin?came_from=257&utm_medium=web&utm_source=home&utm_campaign=ticket_rsvp",
            "fallbackImageUrl": "https://assets.prod.bandsintown.com/images/homeIcon/festivalPlaceHolderImage/02.png",
            "artistName": "Mafia & Fluxy",
            "venueName": "Fox & Firkin",
            "streamingEvent": false,
            "title": null,
            "locationText": "London, United Kingdom",
            "pinIconSrc": "https://assets.prod.bandsintown.com/images/pinIcon.svg",
            "eventUrl": "https://www.bandsintown.com/e/1032959461-mafia-and-fluxy-at-fox-and-firkin?came_from=257&utm_medium=web&utm_source=home&utm_campaign=event",
            "artistUrl": "https://www.bandsintown.com/a/1119765-mafia-and-fluxy?came_from=257&utm_medium=web&utm_source=home&utm_campaign=event",
            "watchLiveText": "Watch Live",
            "isPlus": false,
            "callToActionText": "Tickets & RSVP",
            "rsvpCount": "0",
            "rsvpCountInt": 0,
            "startsAt": "2024-10-10T19:00:00",
            "timezone": "Europe/London",
            "displayRule": "datetime",
            "locale": "en"
        },
        {
            "artistImageSrc": "https://photos.bandsintown.com/thumb/225071.jpeg",
            "properlySizedImageURL": "https://media.bandsintown.com/110x110/225071.webp",
            "callToActionRedirectUrl": "https://www.bandsintown.com/e/1032959335-natty-bo-at-fox-and-firkin?came_from=257&utm_medium=web&utm_source=home&utm_campaign=ticket_rsvp",
            "fallbackImageUrl": "https://assets.prod.bandsintown.com/images/homeIcon/festivalPlaceHolderImage/03.png",
            "artistName": "Natty Bo",
            "venueName": "Fox & Firkin",
            "streamingEvent": false,
            "title": null,
            "locationText": "London, United Kingdom",
            "pinIconSrc": "https://assets.prod.bandsintown.com/images/pinIcon.svg",
            "eventUrl": "https://www.bandsintown.com/e/1032959335-natty-bo-at-fox-and-firkin?came_from=257&utm_medium=web&utm_source=home&utm_campaign=event",
            "artistUrl": "https://www.bandsintown.com/a/282880-natty-bo?came_from=257&utm_medium=web&utm_source=home&utm_campaign=event",
            "watchLiveText": "Watch Live",
            "isPlus": false,
            "callToActionText": "Tickets & RSVP",
            "rsvpCount": "0",
            "rsvpCountInt": 0,
            "startsAt": "2024-10-10T19:00:00",
            "timezone": "Europe/London",
            "displayRule": "datetime",
            "locale": "en"
        },
        {
            "artistImageSrc": "https://photos.bandsintown.com/thumb/146195.jpeg",
            "properlySizedImageURL": "https://media.bandsintown.com/110x110/146195.webp",
            "callToActionRedirectUrl": "https://www.bandsintown.com/e/1032959246-richie-davis-at-fox-and-firkin?came_from=257&utm_medium=web&utm_source=home&utm_campaign=ticket_rsvp",
            "fallbackImageUrl": "https://assets.prod.bandsintown.com/images/homeIcon/festivalPlaceHolderImage/08.png",
            "artistName": "Richie Davis",
            "venueName": "Fox & Firkin",
            "streamingEvent": false,
            "title": null,
            "locationText": "London, United Kingdom",
            "pinIconSrc": "https://assets.prod.bandsintown.com/images/pinIcon.svg",
            "eventUrl": "https://www.bandsintown.com/e/1032959246-richie-davis-at-fox-and-firkin?came_from=257&utm_medium=web&utm_source=home&utm_campaign=event",
            "artistUrl": "https://www.bandsintown.com/a/127244-richie-davis?came_from=257&utm_medium=web&utm_source=home&utm_campaign=event",
            "watchLiveText": "Watch Live",
            "isPlus": false,
            "callToActionText": "Tickets & RSVP",
            "rsvpCount": "1",
            "rsvpCountInt": 1,
            "startsAt": "2024-10-10T19:00:00",
            "timezone": "Europe/London",
            "displayRule": "datetime",
            "locale": "en"
        },
        {
            "artistImageSrc": "https://photos.bandsintown.com/thumb/6053703.jpeg",
            "properlySizedImageURL": "https://media.bandsintown.com/110x110/6053703.webp",
            "callToActionRedirectUrl": "https://www.bandsintown.com/e/1032959234-itch-at-fox-and-firkin?came_from=257&utm_medium=web&utm_source=home&utm_campaign=ticket_rsvp",
            "fallbackImageUrl": "https://assets.prod.bandsintown.com/images/homeIcon/festivalPlaceHolderImage/04.png",
            "artistName": "itch",
            "venueName": "Fox & Firkin",
            "streamingEvent": false,
            "title": null,
            "locationText": "London, United Kingdom",
            "pinIconSrc": "https://assets.prod.bandsintown.com/images/pinIcon.svg",
            "eventUrl": "https://www.bandsintown.com/e/1032959234-itch-at-fox-and-firkin?came_from=257&utm_medium=web&utm_source=home&utm_campaign=event",
            "artistUrl": "https://www.bandsintown.com/a/78756-itch?came_from=257&utm_medium=web&utm_source=home&utm_campaign=event",
            "watchLiveText": "Watch Live",
            "isPlus": false,
            "callToActionText": "Tickets & RSVP",
            "rsvpCount": "6",
            "rsvpCountInt": 6,
            "startsAt": "2024-10-10T19:00:00",
            "timezone": "Europe/London",
            "displayRule": "datetime",
            "locale": "en"
        },
        {
            "artistImageSrc": "https://photos.bandsintown.com/thumb/6354678.jpeg",
            "properlySizedImageURL": "https://media.bandsintown.com/110x110/6354678.webp",
            "callToActionRedirectUrl": "https://www.bandsintown.com/e/1032575032-medusa-at-the-factory-live?came_from=257&utm_medium=web&utm_source=home&utm_campaign=ticket_rsvp",
            "fallbackImageUrl": "https://assets.prod.bandsintown.com/images/homeIcon/festivalPlaceHolderImage/06.png",
            "artistName": "Medusa",
            "venueName": "The Factory Live",
            "streamingEvent": false,
            "title": null,
            "locationText": "Worthing, United Kingdom",
            "pinIconSrc": "https://assets.prod.bandsintown.com/images/pinIcon.svg",
            "eventUrl": "https://www.bandsintown.com/e/1032575032-medusa-at-the-factory-live?came_from=257&utm_medium=web&utm_source=home&utm_campaign=event",
            "artistUrl": "https://www.bandsintown.com/a/18033-medusa?came_from=257&utm_medium=web&utm_source=home&utm_campaign=event",
            "watchLiveText": "Watch Live",
            "isPlus": false,
            "callToActionText": "Tickets & RSVP",
            "rsvpCount": "0",
            "rsvpCountInt": 0,
            "startsAt": "2024-10-10T19:00:00",
            "timezone": "Europe/London",
            "displayRule": "datetime",
            "locale": "en"
        }
    ],
    "urlForNextPageOfEvents": "https://www.bandsintown.com/choose-dates/fetch-next/upcomingEvents?city_id=2643743&date=2024-10-10T00%3A00%3A00%2C2024-10-10T23%3A59%3A59&page=3&longitude=-0.12574&latitude=51.50853&genre_query=all-genres",
    "userLocation": null
}